[
  {
    "code": "1444",
    "symbol": "1444",
    "name": "力麗",
    "market": "上市",
    "industry": "紡織纖維",
    "concepts": [
      "紡織纖維"
    ],
    "close": 10.0,
    "changePercent": 6.95,
    "volume": 27616757,
    "tradeValue": 274099589.0,
    "listedShares": 995595059,
    "turnoverRate": 2.7739,
    "peRatio": null,
    "pbRatio": 1.02,
    "dividendYield": null,
    "revenueMonth": "2026-05",
    "revenueMillion": 1072.31,
    "revenueMomPct": 72.05,
    "revenueYoyPct": 81.02,
    "fundamentalScore": 84.7,
    "technicalScore": 70,
    "chipScore": 71.6,
    "turnoverScore": 87.8,
    "totalScore": 77.5,
    "tradeType": "波段",
    "riskLabel": "正常",
    "updatedAt": "2026-07-04T01:08:05+08:00",
    "dataDate": "2026-07-02",
    "scoreSource": "official_quote_valuation_revenue",
    "rank": 1
  },
  {
    "code": "2359",
    "symbol": "2359",
    "name": "所羅門",
    "market": "上市",
    "industry": "其他電子業",
    "concepts": [
      "其他電子業"
    ],
    "close": 146.5,
    "changePercent": 9.74,
    "volume": 10260130,
    "tradeValue": 1471139487.0,
    "listedShares": 171471052,
    "turnoverRate": 5.9836,
    "peRatio": 75.52,
    "pbRatio": 4.37,
    "dividendYield": 0.68,
    "revenueMonth": "2026-05",
    "revenueMillion": 525.75,
    "revenueMomPct": 47.2,
    "revenueYoyPct": 66.8,
    "fundamentalScore": 65.6,
    "technicalScore": 70,
    "chipScore": 89.3,
    "turnoverScore": 92.8,
    "totalScore": 76.9,
    "tradeType": "波段",
    "riskLabel": "過熱",
    "updatedAt": "2026-07-04T01:08:05+08:00",
    "dataDate": "2026-07-02",
    "scoreSource": "official_quote_valuation_revenue",
    "rank": 2
  },
  {
    "code": "3022",
    "symbol": "3022",
    "name": "威強電",
    "market": "上市",
    "industry": "電腦及週邊設備業",
    "concepts": [
      "電腦及週邊設備業"
    ],
    "close": 87.0,
    "changePercent": 4.95,
    "volume": 4641293,
    "tradeValue": 398861078.0,
    "listedShares": 176597790,
    "turnoverRate": 2.6282,
    "peRatio": 24.65,
    "pbRatio": 1.34,
    "dividendYield": 4.02,
    "revenueMonth": "2026-05",
    "revenueMillion": 888.59,
    "revenueMomPct": 39.29,
    "revenueYoyPct": 92.4,
    "fundamentalScore": 75.8,
    "technicalScore": 66.8,
    "chipScore": 82.3,
    "turnoverScore": 87.0,
    "totalScore": 76.4,
    "tradeType": "中長期",
    "riskLabel": "正常",
    "updatedAt": "2026-07-04T01:08:05+08:00",
    "dataDate": "2026-07-02",
    "scoreSource": "official_quote_valuation_revenue",
    "rank": 3
  },
  {
    "code": "6191",
    "symbol": "6191",
    "name": "精成科",
    "market": "上市",
    "industry": "電子零組件業",
    "concepts": [
      "電子零組件業"
    ],
    "close": 110.0,
    "changePercent": 6.28,
    "volume": 32534052,
    "tradeValue": 3598754466.0,
    "listedShares": 499303000,
    "turnoverRate": 6.5159,
    "peRatio": 17.13,
    "pbRatio": 1.98,
    "dividendYield": 2.36,
    "revenueMonth": "2026-05",
    "revenueMillion": 3298.68,
    "revenueMomPct": 2.86,
    "revenueYoyPct": -2.48,
    "fundamentalScore": 62.4,
    "technicalScore": 70,
    "chipScore": 89.3,
    "turnoverScore": 93.1,
    "totalScore": 76.0,
    "tradeType": "波段",
    "riskLabel": "過熱",
    "updatedAt": "2026-07-04T01:08:05+08:00",
    "dataDate": "2026-07-02",
    "scoreSource": "official_quote_valuation_revenue",
    "rank": 4
  },
  {
    "code": "1409",
    "symbol": "1409",
    "name": "新纖",
    "market": "上市",
    "industry": "紡織纖維",
    "concepts": [
      "紡織纖維"
    ],
    "close": 28.2,
    "changePercent": 9.94,
    "volume": 37366627,
    "tradeValue": 1011426783.0,
    "listedShares": 1618409286,
    "turnoverRate": 2.3088,
    "peRatio": 20.89,
    "pbRatio": 1.08,
    "dividendYield": 3.19,
    "revenueMonth": "2026-05",
    "revenueMillion": 4373.93,
    "revenueMomPct": 7.22,
    "revenueYoyPct": 35.13,
    "fundamentalScore": 69.1,
    "technicalScore": 70,
    "chipScore": 84.7,
    "turnoverScore": 86.1,
    "totalScore": 75.8,
    "tradeType": "波段",
    "riskLabel": "過熱",
    "updatedAt": "2026-07-04T01:08:05+08:00",
    "dataDate": "2026-07-02",
    "scoreSource": "official_quote_valuation_revenue",
    "rank": 5
  },
  {
    "code": "3605",
    "symbol": "3605",
    "name": "宏致",
    "market": "上市",
    "industry": "電子零組件業",
    "concepts": [
      "電子零組件業"
    ],
    "close": 90.1,
    "changePercent": 5.26,
    "volume": 31356003,
    "tradeValue": 2784276916.0,
    "listedShares": 174697441,
    "turnoverRate": 17.9487,
    "peRatio": 26.04,
    "pbRatio": 1.85,
    "dividendYield": 1.86,
    "revenueMonth": "2026-05",
    "revenueMillion": 1108.23,
    "revenueMomPct": -1.46,
    "revenueYoyPct": 15.34,
    "fundamentalScore": 61.1,
    "technicalScore": 67.8,
    "chipScore": 88.7,
    "turnoverScore": 94.4,
    "totalScore": 75.0,
    "tradeType": "中長期",
    "riskLabel": "過熱",
    "updatedAt": "2026-07-04T01:08:05+08:00",
    "dataDate": "2026-07-02",
    "scoreSource": "official_quote_valuation_revenue",
    "rank": 6
  },
  {
    "code": "1708",
    "symbol": "1708",
    "name": "東鹼",
    "market": "上市",
    "industry": "化學工業",
    "concepts": [
      "化學工業"
    ],
    "close": 57.0,
    "changePercent": 9.83,
    "volume": 18115679,
    "tradeValue": 998686166.0,
    "listedShares": 249001651,
    "turnoverRate": 7.2753,
    "peRatio": 16.91,
    "pbRatio": 1.92,
    "dividendYield": 2.81,
    "revenueMonth": "2026-05",
    "revenueMillion": 538.7,
    "revenueMomPct": -22.68,
    "revenueYoyPct": 18.38,
    "fundamentalScore": 61.9,
    "technicalScore": 70,
    "chipScore": 85.3,
    "turnoverScore": 93.4,
    "totalScore": 74.9,
    "tradeType": "波段",
    "riskLabel": "過熱",
    "updatedAt": "2026-07-04T01:08:05+08:00",
    "dataDate": "2026-07-02",
    "scoreSource": "official_quote_valuation_revenue",
    "rank": 7
  },
  {
    "code": "2401",
    "symbol": "2401",
    "name": "凌陽",
    "market": "上市",
    "industry": "半導體業",
    "concepts": [
      "半導體業"
    ],
    "close": 34.3,
    "changePercent": 9.94,
    "volume": 19151783,
    "tradeValue": 644714888.0,
    "listedShares": 591994919,
    "turnoverRate": 3.2351,
    "peRatio": null,
    "pbRatio": 2.46,
    "dividendYield": null,
    "revenueMonth": "2026-05",
    "revenueMillion": 724.38,
    "revenueMomPct": 5.79,
    "revenueYoyPct": 28.67,
    "fundamentalScore": 66.9,
    "technicalScore": 70,
    "chipScore": 80.9,
    "turnoverScore": 89.4,
    "totalScore": 74.7,
    "tradeType": "波段",
    "riskLabel": "過熱",
    "updatedAt": "2026-07-04T01:08:05+08:00",
    "dataDate": "2026-07-02",
    "scoreSource": "official_quote_valuation_revenue",
    "rank": 8
  },
  {
    "code": "3042",
    "symbol": "3042",
    "name": "晶技",
    "market": "上市",
    "industry": "電子零組件業",
    "concepts": [
      "電子零組件業"
    ],
    "close": 226.5,
    "changePercent": 9.95,
    "volume": 74769157,
    "tradeValue": 16212557826.0,
    "listedShares": 342992971,
    "turnoverRate": 21.799,
    "peRatio": 43.23,
    "pbRatio": 5.09,
    "dividendYield": 2.12,
    "revenueMonth": "2026-05",
    "revenueMillion": 1217.16,
    "revenueMomPct": -5.55,
    "revenueYoyPct": 10.5,
    "fundamentalScore": 52.0,
    "technicalScore": 70,
    "chipScore": 95.5,
    "turnoverScore": 94.6,
    "totalScore": 74.7,
    "tradeType": "波段",
    "riskLabel": "過熱",
    "updatedAt": "2026-07-04T01:08:05+08:00",
    "dataDate": "2026-07-02",
    "scoreSource": "official_quote_valuation_revenue",
    "rank": 9
  },
  {
    "code": "2404",
    "symbol": "2404",
    "name": "漢唐",
    "market": "上市",
    "industry": "其他電子業",
    "concepts": [
      "其他電子業"
    ],
    "close": 1385.0,
    "changePercent": 6.54,
    "volume": 3745997,
    "tradeValue": 5058124410.0,
    "listedShares": 190586698,
    "turnoverRate": 1.9655,
    "peRatio": 25.74,
    "pbRatio": 18.19,
    "dividendYield": 2.89,
    "revenueMonth": "2026-05",
    "revenueMillion": 9217.81,
    "revenueMomPct": 13.7,
    "revenueYoyPct": 85.01,
    "fundamentalScore": 65.4,
    "technicalScore": 70,
    "chipScore": 84.7,
    "turnoverScore": 84.7,
    "totalScore": 74.5,
    "tradeType": "波段",
    "riskLabel": "正常",
    "updatedAt": "2026-07-04T01:08:05+08:00",
    "dataDate": "2026-07-02",
    "scoreSource": "official_quote_valuation_revenue",
    "rank": 10
  },
  {
    "code": "2484",
    "symbol": "2484",
    "name": "希華",
    "market": "上市",
    "industry": "電子零組件業",
    "concepts": [
      "電子零組件業"
    ],
    "close": 87.7,
    "changePercent": 9.9,
    "volume": 70000147,
    "tradeValue": 5876303997.0,
    "listedShares": 159421022,
    "turnoverRate": 43.909,
    "peRatio": 118.51,
    "pbRatio": 3.41,
    "dividendYield": 0.8,
    "revenueMonth": "2026-05",
    "revenueMillion": 214.84,
    "revenueMomPct": -8.07,
    "revenueYoyPct": 4.72,
    "fundamentalScore": 51.5,
    "technicalScore": 70,
    "chipScore": 93.2,
    "turnoverScore": 95.0,
    "totalScore": 74.0,
    "tradeType": "波段",
    "riskLabel": "過熱",
    "updatedAt": "2026-07-04T01:08:05+08:00",
    "dataDate": "2026-07-02",
    "scoreSource": "official_quote_valuation_revenue",
    "rank": 11
  },
  {
    "code": "1536",
    "symbol": "1536",
    "name": "和大",
    "market": "上市",
    "industry": "汽車工業",
    "concepts": [
      "汽車工業"
    ],
    "close": 50.9,
    "changePercent": 6.49,
    "volume": 9250012,
    "tradeValue": 465237757.0,
    "listedShares": 278959513,
    "turnoverRate": 3.3159,
    "peRatio": null,
    "pbRatio": 1.89,
    "dividendYield": null,
    "revenueMonth": "2026-05",
    "revenueMillion": 394.75,
    "revenueMomPct": -2.58,
    "revenueYoyPct": 12.16,
    "fundamentalScore": 60.8,
    "technicalScore": 70,
    "chipScore": 84.9,
    "turnoverScore": 89.5,
    "totalScore": 73.9,
    "tradeType": "波段",
    "riskLabel": "正常",
    "updatedAt": "2026-07-04T01:08:05+08:00",
    "dataDate": "2026-07-02",
    "scoreSource": "official_quote_valuation_revenue",
    "rank": 12
  },
  {
    "code": "3019",
    "symbol": "3019",
    "name": "亞光",
    "market": "上市",
    "industry": "光電業",
    "concepts": [
      "光電業"
    ],
    "close": 149.5,
    "changePercent": 6.79,
    "volume": 7512145,
    "tradeValue": 1109516999.0,
    "listedShares": 279243901,
    "turnoverRate": 2.6902,
    "peRatio": 21.79,
    "pbRatio": 2.92,
    "dividendYield": 3.08,
    "revenueMonth": "2026-05",
    "revenueMillion": 2624.0,
    "revenueMomPct": 5.38,
    "revenueYoyPct": 16.24,
    "fundamentalScore": 61.8,
    "technicalScore": 70,
    "chipScore": 85.2,
    "turnoverScore": 87.3,
    "totalScore": 73.9,
    "tradeType": "波段",
    "riskLabel": "正常",
    "updatedAt": "2026-07-04T01:08:05+08:00",
    "dataDate": "2026-07-02",
    "scoreSource": "official_quote_valuation_revenue",
    "rank": 13
  },
  {
    "code": "4989",
    "symbol": "4989",
    "name": "榮科",
    "market": "上市",
    "industry": "電子零組件業",
    "concepts": [
      "電子零組件業"
    ],
    "close": 100.5,
    "changePercent": 9.48,
    "volume": 24009502,
    "tradeValue": 2366918276.0,
    "listedShares": 137776500,
    "turnoverRate": 17.4264,
    "peRatio": null,
    "pbRatio": 9.33,
    "dividendYield": null,
    "revenueMonth": "2026-05",
    "revenueMillion": 323.36,
    "revenueMomPct": -14.76,
    "revenueYoyPct": 33.87,
    "fundamentalScore": 54.6,
    "technicalScore": 70,
    "chipScore": 87.7,
    "turnoverScore": 94.4,
    "totalScore": 73.5,
    "tradeType": "波段",
    "riskLabel": "過熱",
    "updatedAt": "2026-07-04T01:08:05+08:00",
    "dataDate": "2026-07-02",
    "scoreSource": "official_quote_valuation_revenue",
    "rank": 14
  },
  {
    "code": "8261",
    "symbol": "8261",
    "name": "富鼎",
    "market": "上市",
    "industry": "半導體業",
    "concepts": [
      "半導體業"
    ],
    "close": 327.0,
    "changePercent": 9.92,
    "volume": 29470640,
    "tradeValue": 9152870649.0,
    "listedShares": 118878393,
    "turnoverRate": 24.7906,
    "peRatio": 55.99,
    "pbRatio": 6.35,
    "dividendYield": 1.53,
    "revenueMonth": "2026-05",
    "revenueMillion": 296.82,
    "revenueMomPct": 4.55,
    "revenueYoyPct": 1.15,
    "fundamentalScore": 51.4,
    "technicalScore": 70,
    "chipScore": 91.4,
    "turnoverScore": 94.7,
    "totalScore": 73.5,
    "tradeType": "波段",
    "riskLabel": "過熱",
    "updatedAt": "2026-07-04T01:08:05+08:00",
    "dataDate": "2026-07-02",
    "scoreSource": "official_quote_valuation_revenue",
    "rank": 15
  },
  {
    "code": "3706",
    "symbol": "3706",
    "name": "神達",
    "market": "上市",
    "industry": "電腦及週邊設備業",
    "concepts": [
      "電腦及週邊設備業"
    ],
    "close": 93.3,
    "changePercent": 2.19,
    "volume": 36037435,
    "tradeValue": 3319077623.0,
    "listedShares": 1327212468,
    "turnoverRate": 2.7153,
    "peRatio": 17.81,
    "pbRatio": 1.86,
    "dividendYield": 4.29,
    "revenueMonth": "2026-05",
    "revenueMillion": 13638.5,
    "revenueMomPct": 17.24,
    "revenueYoyPct": 49.3,
    "fundamentalScore": 74.7,
    "technicalScore": 58.6,
    "chipScore": 81.1,
    "turnoverScore": 87.3,
    "totalScore": 73.4,
    "tradeType": "中長期",
    "riskLabel": "正常",
    "updatedAt": "2026-07-04T01:08:05+08:00",
    "dataDate": "2026-07-02",
    "scoreSource": "official_quote_valuation_revenue",
    "rank": 16
  },
  {
    "code": "3443",
    "symbol": "3443",
    "name": "創意",
    "market": "上市",
    "industry": "半導體業",
    "concepts": [
      "半導體業"
    ],
    "close": 5330.0,
    "changePercent": 5.65,
    "volume": 3217683,
    "tradeValue": 16661121045.0,
    "listedShares": 134011911,
    "turnoverRate": 2.401,
    "peRatio": 160.35,
    "pbRatio": 48.98,
    "dividendYield": 0.38,
    "revenueMonth": "2026-05",
    "revenueMillion": 4674.01,
    "revenueMomPct": 8.85,
    "revenueYoyPct": 132.13,
    "fundamentalScore": 57.7,
    "technicalScore": 69.0,
    "chipScore": 89.4,
    "turnoverScore": 86.4,
    "totalScore": 73.3,
    "tradeType": "波段",
    "riskLabel": "正常",
    "updatedAt": "2026-07-04T01:08:05+08:00",
    "dataDate": "2026-07-02",
    "scoreSource": "official_quote_valuation_revenue",
    "rank": 17
  },
  {
    "code": "3550",
    "symbol": "3550",
    "name": "聯穎",
    "market": "上市",
    "industry": "電子零組件業",
    "concepts": [
      "電子零組件業"
    ],
    "close": 36.7,
    "changePercent": 9.88,
    "volume": 13098609,
    "tradeValue": 474816214.0,
    "listedShares": 107550000,
    "turnoverRate": 12.1791,
    "peRatio": null,
    "pbRatio": 2.36,
    "dividendYield": null,
    "revenueMonth": "2026-05",
    "revenueMillion": 391.68,
    "revenueMomPct": -12.6,
    "revenueYoyPct": 36.57,
    "fundamentalScore": 63.8,
    "technicalScore": 70,
    "chipScore": 76.0,
    "turnoverScore": 94.2,
    "totalScore": 73.3,
    "tradeType": "波段",
    "riskLabel": "過熱",
    "updatedAt": "2026-07-04T01:08:05+08:00",
    "dataDate": "2026-07-02",
    "scoreSource": "official_quote_valuation_revenue",
    "rank": 18
  },
  {
    "code": "6215",
    "symbol": "6215",
    "name": "和椿",
    "market": "上市",
    "industry": "其他電子業",
    "concepts": [
      "其他電子業"
    ],
    "close": 118.0,
    "changePercent": 9.26,
    "volume": 9410508,
    "tradeValue": 1097616459.0,
    "listedShares": 82789693,
    "turnoverRate": 11.3668,
    "peRatio": 41.4,
    "pbRatio": 6.02,
    "dividendYield": 0.85,
    "revenueMonth": "2026-05",
    "revenueMillion": 290.67,
    "revenueMomPct": -12.59,
    "revenueYoyPct": 37.91,
    "fundamentalScore": 52.9,
    "technicalScore": 70,
    "chipScore": 89.1,
    "turnoverScore": 94.1,
    "totalScore": 73.3,
    "tradeType": "波段",
    "riskLabel": "過熱",
    "updatedAt": "2026-07-04T01:08:05+08:00",
    "dataDate": "2026-07-02",
    "scoreSource": "official_quote_valuation_revenue",
    "rank": 19
  },
  {
    "code": "2406",
    "symbol": "2406",
    "name": "國碩",
    "market": "上市",
    "industry": "光電業",
    "concepts": [
      "光電業"
    ],
    "close": 41.75,
    "changePercent": 3.86,
    "volume": 66279658,
    "tradeValue": 2799286286.0,
    "listedShares": 350905689,
    "turnoverRate": 18.8882,
    "peRatio": null,
    "pbRatio": 4.01,
    "dividendYield": null,
    "revenueMonth": "2026-05",
    "revenueMillion": 960.59,
    "revenueMomPct": -8.8,
    "revenueYoyPct": 121.2,
    "fundamentalScore": 65.0,
    "technicalScore": 63.6,
    "chipScore": 81.6,
    "turnoverScore": 94.5,
    "totalScore": 73.2,
    "tradeType": "中長期",
    "riskLabel": "過熱",
    "updatedAt": "2026-07-04T01:08:05+08:00",
    "dataDate": "2026-07-02",
    "scoreSource": "official_quote_valuation_revenue",
    "rank": 20
  },
  {
    "code": "1301",
    "symbol": "1301",
    "name": "台塑",
    "market": "上市",
    "industry": "塑膠工業",
    "concepts": [
      "塑膠工業"
    ],
    "close": 59.7,
    "changePercent": 9.94,
    "volume": 112956008,
    "tradeValue": 6568856495.0,
    "listedShares": 6365740781,
    "turnoverRate": 1.7744,
    "peRatio": null,
    "pbRatio": 0.97,
    "dividendYield": 0.84,
    "revenueMonth": "2026-05",
    "revenueMillion": 14951.42,
    "revenueMomPct": -18.42,
    "revenueYoyPct": 0.67,
    "fundamentalScore": 55.7,
    "technicalScore": 70,
    "chipScore": 91.3,
    "turnoverScore": 83.7,
    "totalScore": 73.1,
    "tradeType": "波段",
    "riskLabel": "過熱",
    "updatedAt": "2026-07-04T01:08:05+08:00",
    "dataDate": "2026-07-02",
    "scoreSource": "official_quote_valuation_revenue",
    "rank": 21
  },
  {
    "code": "2340",
    "symbol": "2340",
    "name": "台亞",
    "market": "上市",
    "industry": "半導體業",
    "concepts": [
      "半導體業"
    ],
    "close": 38.65,
    "changePercent": 9.96,
    "volume": 13108516,
    "tradeValue": 497318542.0,
    "listedShares": 438622846,
    "turnoverRate": 2.9886,
    "peRatio": null,
    "pbRatio": 2.67,
    "dividendYield": null,
    "revenueMonth": "2026-05",
    "revenueMillion": 407.47,
    "revenueMomPct": 27.78,
    "revenueYoyPct": 5.66,
    "fundamentalScore": 63.7,
    "technicalScore": 70,
    "chipScore": 78.3,
    "turnoverScore": 88.7,
    "totalScore": 73.0,
    "tradeType": "波段",
    "riskLabel": "過熱",
    "updatedAt": "2026-07-04T01:08:05+08:00",
    "dataDate": "2026-07-02",
    "scoreSource": "official_quote_valuation_revenue",
    "rank": 22
  },
  {
    "code": "4916",
    "symbol": "4916",
    "name": "事欣科",
    "market": "上市",
    "industry": "電腦及週邊設備業",
    "concepts": [
      "電腦及週邊設備業"
    ],
    "close": 115.0,
    "changePercent": 2.22,
    "volume": 29875027,
    "tradeValue": 3388723136.0,
    "listedShares": 123714073,
    "turnoverRate": 24.1484,
    "peRatio": 20.5,
    "pbRatio": 3.89,
    "dividendYield": 0.43,
    "revenueMonth": "2026-05",
    "revenueMillion": 450.45,
    "revenueMomPct": 6.05,
    "revenueYoyPct": 104.35,
    "fundamentalScore": 63.4,
    "technicalScore": 58.7,
    "chipScore": 88.2,
    "turnoverScore": 94.7,
    "totalScore": 72.9,
    "tradeType": "中長期",
    "riskLabel": "過熱",
    "updatedAt": "2026-07-04T01:08:05+08:00",
    "dataDate": "2026-07-02",
    "scoreSource": "official_quote_valuation_revenue",
    "rank": 23
  },
  {
    "code": "2476",
    "symbol": "2476",
    "name": "鉅祥",
    "market": "上市",
    "industry": "電子零組件業",
    "concepts": [
      "電子零組件業"
    ],
    "close": 134.0,
    "changePercent": 4.28,
    "volume": 6273570,
    "tradeValue": 820679731.0,
    "listedShares": 218080998,
    "turnoverRate": 2.8767,
    "peRatio": 30.66,
    "pbRatio": 3.15,
    "dividendYield": 2.24,
    "revenueMonth": "2026-05",
    "revenueMillion": 838.72,
    "revenueMomPct": 3.13,
    "revenueYoyPct": 48.67,
    "fundamentalScore": 64.9,
    "technicalScore": 64.8,
    "chipScore": 81.2,
    "turnoverScore": 88.0,
    "totalScore": 72.4,
    "tradeType": "中長期",
    "riskLabel": "正常",
    "updatedAt": "2026-07-04T01:08:05+08:00",
    "dataDate": "2026-07-02",
    "scoreSource": "official_quote_valuation_revenue",
    "rank": 24
  },
  {
    "code": "6442",
    "symbol": "6442",
    "name": "光聖",
    "market": "上市",
    "industry": "通信網路業",
    "concepts": [
      "通信網路業"
    ],
    "close": 1635.0,
    "changePercent": 3.81,
    "volume": 2212614,
    "tradeValue": 3461642200.0,
    "listedShares": 78073288,
    "turnoverRate": 2.834,
    "peRatio": 61.67,
    "pbRatio": 18.06,
    "dividendYield": 0.72,
    "revenueMonth": "2026-05",
    "revenueMillion": 1725.67,
    "revenueMomPct": 94.67,
    "revenueYoyPct": 116.02,
    "fundamentalScore": 63.0,
    "technicalScore": 63.4,
    "chipScore": 85.4,
    "turnoverScore": 87.8,
    "totalScore": 72.4,
    "tradeType": "中長期",
    "riskLabel": "正常",
    "updatedAt": "2026-07-04T01:08:05+08:00",
    "dataDate": "2026-07-02",
    "scoreSource": "official_quote_valuation_revenue",
    "rank": 25
  },
  {
    "code": "6525",
    "symbol": "6525",
    "name": "捷敏-KY",
    "market": "上市",
    "industry": "半導體業",
    "concepts": [
      "半導體業"
    ],
    "close": 166.5,
    "changePercent": 9.9,
    "volume": 3776046,
    "tradeValue": 612854875.0,
    "listedShares": 129047384,
    "turnoverRate": 2.9261,
    "peRatio": 27.43,
    "pbRatio": 4.9,
    "dividendYield": 3.0,
    "revenueMonth": "2026-05",
    "revenueMillion": 548.58,
    "revenueMomPct": 1.65,
    "revenueYoyPct": 18.95,
    "fundamentalScore": 61.5,
    "technicalScore": 70,
    "chipScore": 78.8,
    "turnoverScore": 88.3,
    "totalScore": 72.4,
    "tradeType": "波段",
    "riskLabel": "過熱",
    "updatedAt": "2026-07-04T01:08:05+08:00",
    "dataDate": "2026-07-02",
    "scoreSource": "official_quote_valuation_revenue",
    "rank": 26
  },
  {
    "code": "2374",
    "symbol": "2374",
    "name": "佳能",
    "market": "上市",
    "industry": "光電業",
    "concepts": [
      "光電業"
    ],
    "close": 77.0,
    "changePercent": 4.76,
    "volume": 9890740,
    "tradeValue": 759156538.0,
    "listedShares": 337992133,
    "turnoverRate": 2.9263,
    "peRatio": 27.7,
    "pbRatio": 2.9,
    "dividendYield": 2.6,
    "revenueMonth": "2026-05",
    "revenueMillion": 1005.8,
    "revenueMomPct": -6.99,
    "revenueYoyPct": 27.82,
    "fundamentalScore": 60.8,
    "technicalScore": 66.3,
    "chipScore": 83.8,
    "turnoverScore": 88.3,
    "totalScore": 72.3,
    "tradeType": "中長期",
    "riskLabel": "正常",
    "updatedAt": "2026-07-04T01:08:05+08:00",
    "dataDate": "2026-07-02",
    "scoreSource": "official_quote_valuation_revenue",
    "rank": 27
  },
  {
    "code": "4540",
    "symbol": "4540",
    "name": "全球傳動",
    "market": "上市",
    "industry": "電機機械",
    "concepts": [
      "電機機械"
    ],
    "close": 62.3,
    "changePercent": 9.88,
    "volume": 3971337,
    "tradeValue": 242914865.0,
    "listedShares": 115186724,
    "turnoverRate": 3.4477,
    "peRatio": null,
    "pbRatio": 2.09,
    "dividendYield": null,
    "revenueMonth": "2026-05",
    "revenueMillion": 243.01,
    "revenueMomPct": -4.42,
    "revenueYoyPct": 22.97,
    "fundamentalScore": 62.8,
    "technicalScore": 70,
    "chipScore": 75.9,
    "turnoverScore": 89.6,
    "totalScore": 72.3,
    "tradeType": "波段",
    "riskLabel": "過熱",
    "updatedAt": "2026-07-04T01:08:05+08:00",
    "dataDate": "2026-07-02",
    "scoreSource": "official_quote_valuation_revenue",
    "rank": 28
  },
  {
    "code": "4590",
    "symbol": "4590",
    "name": "富田-創",
    "market": "上市",
    "industry": "電機機械",
    "concepts": [
      "電機機械"
    ],
    "close": 88.0,
    "changePercent": 10.0,
    "volume": 1206514,
    "tradeValue": 104302695.0,
    "listedShares": 54838400,
    "turnoverRate": 2.2001,
    "peRatio": 34.65,
    "pbRatio": 1.37,
    "dividendYield": 2.61,
    "revenueMonth": "2026-05",
    "revenueMillion": 108.58,
    "revenueMomPct": 47.99,
    "revenueYoyPct": 10.98,
    "fundamentalScore": 68.0,
    "technicalScore": 70,
    "chipScore": 72.3,
    "turnoverScore": 85.8,
    "totalScore": 72.3,
    "tradeType": "波段",
    "riskLabel": "過熱",
    "updatedAt": "2026-07-04T01:08:05+08:00",
    "dataDate": "2026-07-02",
    "scoreSource": "official_quote_valuation_revenue",
    "rank": 29
  },
  {
    "code": "6515",
    "symbol": "6515",
    "name": "穎崴",
    "market": "上市",
    "industry": "半導體業",
    "concepts": [
      "半導體業"
    ],
    "close": 9310.0,
    "changePercent": 4.72,
    "volume": 614919,
    "tradeValue": 5664214055.0,
    "listedShares": 36038042,
    "turnoverRate": 1.7063,
    "peRatio": 190.78,
    "pbRatio": 51.64,
    "dividendYield": 0.54,
    "revenueMonth": "2026-05",
    "revenueMillion": 1073.48,
    "revenueMomPct": 8.48,
    "revenueYoyPct": 119.79,
    "fundamentalScore": 57.9,
    "technicalScore": 66.2,
    "chipScore": 90.3,
    "turnoverScore": 83.1,
    "totalScore": 72.3,
    "tradeType": "中長期",
    "riskLabel": "正常",
    "updatedAt": "2026-07-04T01:08:05+08:00",
    "dataDate": "2026-07-02",
    "scoreSource": "official_quote_valuation_revenue",
    "rank": 30
  },
  {
    "code": "2399",
    "symbol": "2399",
    "name": "映泰",
    "market": "上市",
    "industry": "電腦及週邊設備業",
    "concepts": [
      "電腦及週邊設備業"
    ],
    "close": 51.5,
    "changePercent": 3.62,
    "volume": 14838157,
    "tradeValue": 757067384.0,
    "listedShares": 178100000,
    "turnoverRate": 8.3314,
    "peRatio": 33.01,
    "pbRatio": 3.72,
    "dividendYield": null,
    "revenueMonth": "2026-05",
    "revenueMillion": 191.78,
    "revenueMomPct": 7.66,
    "revenueYoyPct": 48.24,
    "fundamentalScore": 66.7,
    "technicalScore": 62.9,
    "chipScore": 77.1,
    "turnoverScore": 93.7,
    "totalScore": 72.2,
    "tradeType": "中長期",
    "riskLabel": "過熱",
    "updatedAt": "2026-07-04T01:08:05+08:00",
    "dataDate": "2026-07-02",
    "scoreSource": "official_quote_valuation_revenue",
    "rank": 31
  },
  {
    "code": "3016",
    "symbol": "3016",
    "name": "嘉晶",
    "market": "上市",
    "industry": "半導體業",
    "concepts": [
      "半導體業"
    ],
    "close": 134.0,
    "changePercent": 9.84,
    "volume": 28157674,
    "tradeValue": 3674554856.0,
    "listedShares": 288541819,
    "turnoverRate": 9.7586,
    "peRatio": 326.83,
    "pbRatio": 7.9,
    "dividendYield": 0.37,
    "revenueMonth": "2026-05",
    "revenueMillion": 433.76,
    "revenueMomPct": 1.67,
    "revenueYoyPct": 37.28,
    "fundamentalScore": 54.4,
    "technicalScore": 70,
    "chipScore": 83.3,
    "turnoverScore": 93.8,
    "totalScore": 72.2,
    "tradeType": "波段",
    "riskLabel": "過熱",
    "updatedAt": "2026-07-04T01:08:05+08:00",
    "dataDate": "2026-07-02",
    "scoreSource": "official_quote_valuation_revenue",
    "rank": 32
  },
  {
    "code": "3563",
    "symbol": "3563",
    "name": "牧德",
    "market": "上市",
    "industry": "光電業",
    "concepts": [
      "光電業"
    ],
    "close": 809.0,
    "changePercent": 3.98,
    "volume": 4120487,
    "tradeValue": 3335855448.0,
    "listedShares": 63960858,
    "turnoverRate": 6.4422,
    "peRatio": 51.66,
    "pbRatio": 9.93,
    "dividendYield": 1.73,
    "revenueMonth": "2026-05",
    "revenueMillion": 349.02,
    "revenueMomPct": 1.68,
    "revenueYoyPct": 5.14,
    "fundamentalScore": 51.8,
    "technicalScore": 63.9,
    "chipScore": 94.3,
    "turnoverScore": 93.0,
    "totalScore": 72.2,
    "tradeType": "中長期",
    "riskLabel": "過熱",
    "updatedAt": "2026-07-04T01:08:05+08:00",
    "dataDate": "2026-07-02",
    "scoreSource": "official_quote_valuation_revenue",
    "rank": 33
  },
  {
    "code": "3673",
    "symbol": "3673",
    "name": "TPK-KY",
    "market": "上市",
    "industry": "光電業",
    "concepts": [
      "光電業"
    ],
    "close": 83.8,
    "changePercent": 9.97,
    "volume": 12382845,
    "tradeValue": 1009601852.0,
    "listedShares": 406663759,
    "turnoverRate": 3.045,
    "peRatio": 23.02,
    "pbRatio": 0.84,
    "dividendYield": 2.15,
    "revenueMonth": "2026-05",
    "revenueMillion": 6149.32,
    "revenueMomPct": -9.62,
    "revenueYoyPct": -2.6,
    "fundamentalScore": 59.7,
    "technicalScore": 70,
    "chipScore": 79.8,
    "turnoverScore": 88.8,
    "totalScore": 72.2,
    "tradeType": "波段",
    "riskLabel": "過熱",
    "updatedAt": "2026-07-04T01:08:05+08:00",
    "dataDate": "2026-07-02",
    "scoreSource": "official_quote_valuation_revenue",
    "rank": 34
  },
  {
    "code": "2486",
    "symbol": "2486",
    "name": "一詮",
    "market": "上市",
    "industry": "光電業",
    "concepts": [
      "光電業"
    ],
    "close": 254.0,
    "changePercent": 9.96,
    "volume": 8482363,
    "tradeValue": 2109770685.0,
    "listedShares": 233958579,
    "turnoverRate": 3.6256,
    "peRatio": 498.04,
    "pbRatio": 11.27,
    "dividendYield": 0.2,
    "revenueMonth": "2026-05",
    "revenueMillion": 693.51,
    "revenueMomPct": 3.96,
    "revenueYoyPct": 31.37,
    "fundamentalScore": 53.7,
    "technicalScore": 70,
    "chipScore": 85.7,
    "turnoverScore": 90.4,
    "totalScore": 72.1,
    "tradeType": "波段",
    "riskLabel": "過熱",
    "updatedAt": "2026-07-04T01:08:05+08:00",
    "dataDate": "2026-07-02",
    "scoreSource": "official_quote_valuation_revenue",
    "rank": 35
  },
  {
    "code": "1326",
    "symbol": "1326",
    "name": "台化",
    "market": "上市",
    "industry": "塑膠工業",
    "concepts": [
      "塑膠工業"
    ],
    "close": 61.9,
    "changePercent": 9.95,
    "volume": 64670626,
    "tradeValue": 3903781242.0,
    "listedShares": 5861186291,
    "turnoverRate": 1.1034,
    "peRatio": 412.67,
    "pbRatio": 0.97,
    "dividendYield": 0.97,
    "revenueMonth": "2026-05",
    "revenueMillion": 27386.9,
    "revenueMomPct": -14.69,
    "revenueYoyPct": 15.45,
    "fundamentalScore": 56.4,
    "technicalScore": 70,
    "chipScore": 88.9,
    "turnoverScore": 78.7,
    "totalScore": 72.0,
    "tradeType": "波段",
    "riskLabel": "過熱",
    "updatedAt": "2026-07-04T01:08:05+08:00",
    "dataDate": "2026-07-02",
    "scoreSource": "official_quote_valuation_revenue",
    "rank": 36
  },
  {
    "code": "2105",
    "symbol": "2105",
    "name": "正新",
    "market": "上市",
    "industry": "橡膠工業",
    "concepts": [
      "橡膠工業"
    ],
    "close": 31.7,
    "changePercent": 5.32,
    "volume": 24857869,
    "tradeValue": 773826856.0,
    "listedShares": 3241415536,
    "turnoverRate": 0.7669,
    "peRatio": 19.57,
    "pbRatio": 1.21,
    "dividendYield": 5.68,
    "revenueMonth": "2026-05",
    "revenueMillion": 7820.45,
    "revenueMomPct": -9.48,
    "revenueYoyPct": 1.22,
    "fundamentalScore": 65.1,
    "technicalScore": 68.0,
    "chipScore": 84.4,
    "turnoverScore": 72.9,
    "totalScore": 72.0,
    "tradeType": "波段",
    "riskLabel": "正常",
    "updatedAt": "2026-07-04T01:08:05+08:00",
    "dataDate": "2026-07-02",
    "scoreSource": "official_quote_valuation_revenue",
    "rank": 37
  },
  {
    "code": "2233",
    "symbol": "2233",
    "name": "宇隆",
    "market": "上市",
    "industry": "汽車工業",
    "concepts": [
      "汽車工業"
    ],
    "close": 250.0,
    "changePercent": 7.3,
    "volume": 2696769,
    "tradeValue": 645062062.0,
    "listedShares": 60288089,
    "turnoverRate": 4.4731,
    "peRatio": 39.87,
    "pbRatio": 3.77,
    "dividendYield": 1.6,
    "revenueMonth": "2026-05",
    "revenueMillion": 300.1,
    "revenueMomPct": 0.84,
    "revenueYoyPct": 0.96,
    "fundamentalScore": 53.5,
    "technicalScore": 70,
    "chipScore": 84.5,
    "turnoverScore": 91.7,
    "totalScore": 71.9,
    "tradeType": "波段",
    "riskLabel": "過熱",
    "updatedAt": "2026-07-04T01:08:05+08:00",
    "dataDate": "2026-07-02",
    "scoreSource": "official_quote_valuation_revenue",
    "rank": 38
  },
  {
    "code": "2369",
    "symbol": "2369",
    "name": "菱生",
    "market": "上市",
    "industry": "半導體業",
    "concepts": [
      "半導體業"
    ],
    "close": 39.95,
    "changePercent": 4.17,
    "volume": 13436949,
    "tradeValue": 525634886.0,
    "listedShares": 380102344,
    "turnoverRate": 3.5351,
    "peRatio": null,
    "pbRatio": 3.09,
    "dividendYield": null,
    "revenueMonth": "2026-05",
    "revenueMillion": 645.16,
    "revenueMomPct": 12.84,
    "revenueYoyPct": 38.73,
    "fundamentalScore": 67.5,
    "technicalScore": 64.5,
    "chipScore": 75.2,
    "turnoverScore": 90.0,
    "totalScore": 71.9,
    "tradeType": "中長期",
    "riskLabel": "正常",
    "updatedAt": "2026-07-04T01:08:05+08:00",
    "dataDate": "2026-07-02",
    "scoreSource": "official_quote_valuation_revenue",
    "rank": 39
  },
  {
    "code": "4967",
    "symbol": "4967",
    "name": "十銓",
    "market": "上市",
    "industry": "半導體業",
    "concepts": [
      "半導體業"
    ],
    "close": 256.0,
    "changePercent": 2.2,
    "volume": 2654343,
    "tradeValue": 661828934.0,
    "listedShares": 84963288,
    "turnoverRate": 3.1241,
    "peRatio": 6.55,
    "pbRatio": 3.07,
    "dividendYield": 3.91,
    "revenueMonth": "2026-05",
    "revenueMillion": 2555.6,
    "revenueMomPct": 26.84,
    "revenueYoyPct": 112.59,
    "fundamentalScore": 75.6,
    "technicalScore": 58.6,
    "chipScore": 73.1,
    "turnoverScore": 89.2,
    "totalScore": 71.9,
    "tradeType": "中長期",
    "riskLabel": "正常",
    "updatedAt": "2026-07-04T01:08:05+08:00",
    "dataDate": "2026-07-02",
    "scoreSource": "official_quote_valuation_revenue",
    "rank": 40
  },
  {
    "code": "6133",
    "symbol": "6133",
    "name": "金橋",
    "market": "上市",
    "industry": "電子零組件業",
    "concepts": [
      "電子零組件業"
    ],
    "close": 26.25,
    "changePercent": 9.83,
    "volume": 8692937,
    "tradeValue": 223105155.0,
    "listedShares": 117006294,
    "turnoverRate": 7.4295,
    "peRatio": 35.96,
    "pbRatio": 1.92,
    "dividendYield": 3.81,
    "revenueMonth": "2026-05",
    "revenueMillion": 116.82,
    "revenueMomPct": -7.7,
    "revenueYoyPct": 5.36,
    "fundamentalScore": 58.1,
    "technicalScore": 70,
    "chipScore": 77.7,
    "turnoverScore": 93.5,
    "totalScore": 71.9,
    "tradeType": "波段",
    "riskLabel": "過熱",
    "updatedAt": "2026-07-04T01:08:05+08:00",
    "dataDate": "2026-07-02",
    "scoreSource": "official_quote_valuation_revenue",
    "rank": 41
  },
  {
    "code": "3135",
    "symbol": "3135",
    "name": "凌航",
    "market": "上市",
    "industry": "半導體業",
    "concepts": [
      "半導體業"
    ],
    "close": 183.5,
    "changePercent": 9.88,
    "volume": 3428737,
    "tradeValue": 601996636.0,
    "listedShares": 90071491,
    "turnoverRate": 3.8067,
    "peRatio": 12.99,
    "pbRatio": 5.05,
    "dividendYield": 2.56,
    "revenueMonth": "2026-05",
    "revenueMillion": 1841.76,
    "revenueMomPct": -52.2,
    "revenueYoyPct": 234.47,
    "fundamentalScore": 59.2,
    "technicalScore": 70,
    "chipScore": 77.5,
    "turnoverScore": 90.9,
    "totalScore": 71.8,
    "tradeType": "波段",
    "riskLabel": "過熱",
    "updatedAt": "2026-07-04T01:08:05+08:00",
    "dataDate": "2026-07-02",
    "scoreSource": "official_quote_valuation_revenue",
    "rank": 42
  },
  {
    "code": "6278",
    "symbol": "6278",
    "name": "台表科",
    "market": "上市",
    "industry": "光電業",
    "concepts": [
      "光電業"
    ],
    "close": 217.0,
    "changePercent": 4.83,
    "volume": 12750371,
    "tradeValue": 2727209579.0,
    "listedShares": 292398353,
    "turnoverRate": 4.3606,
    "peRatio": 24.77,
    "pbRatio": 2.82,
    "dividendYield": 2.56,
    "revenueMonth": "2026-05",
    "revenueMillion": 4348.04,
    "revenueMomPct": -3.5,
    "revenueYoyPct": 2.43,
    "fundamentalScore": 57.8,
    "technicalScore": 66.5,
    "chipScore": 83.3,
    "turnoverScore": 91.5,
    "totalScore": 71.8,
    "tradeType": "中長期",
    "riskLabel": "正常",
    "updatedAt": "2026-07-04T01:08:05+08:00",
    "dataDate": "2026-07-02",
    "scoreSource": "official_quote_valuation_revenue",
    "rank": 43
  },
  {
    "code": "8271",
    "symbol": "8271",
    "name": "宇瞻",
    "market": "上市",
    "industry": "半導體業",
    "concepts": [
      "半導體業"
    ],
    "close": 192.5,
    "changePercent": 6.94,
    "volume": 2306978,
    "tradeValue": 426643816.0,
    "listedShares": 129614266,
    "turnoverRate": 1.7799,
    "peRatio": 9.38,
    "pbRatio": 3.91,
    "dividendYield": 2.31,
    "revenueMonth": "2026-05",
    "revenueMillion": 3022.79,
    "revenueMomPct": -19.17,
    "revenueYoyPct": 224.43,
    "fundamentalScore": 66.0,
    "technicalScore": 70,
    "chipScore": 73.7,
    "turnoverScore": 83.7,
    "totalScore": 71.8,
    "tradeType": "波段",
    "riskLabel": "正常",
    "updatedAt": "2026-07-04T01:08:05+08:00",
    "dataDate": "2026-07-02",
    "scoreSource": "official_quote_valuation_revenue",
    "rank": 44
  },
  {
    "code": "3015",
    "symbol": "3015",
    "name": "全漢",
    "market": "上市",
    "industry": "電子零組件業",
    "concepts": [
      "電子零組件業"
    ],
    "close": 67.5,
    "changePercent": 3.05,
    "volume": 10621092,
    "tradeValue": 727685573.0,
    "listedShares": 187261950,
    "turnoverRate": 5.6718,
    "peRatio": 33.25,
    "pbRatio": 1.07,
    "dividendYield": 3.26,
    "revenueMonth": "2026-05",
    "revenueMillion": 1114.72,
    "revenueMomPct": 3.67,
    "revenueYoyPct": -9.79,
    "fundamentalScore": 62.4,
    "technicalScore": 61.1,
    "chipScore": 82.8,
    "turnoverScore": 92.6,
    "totalScore": 71.6,
    "tradeType": "中長期",
    "riskLabel": "過熱",
    "updatedAt": "2026-07-04T01:08:05+08:00",
    "dataDate": "2026-07-02",
    "scoreSource": "official_quote_valuation_revenue",
    "rank": 45
  },
  {
    "code": "1515",
    "symbol": "1515",
    "name": "力山",
    "market": "上市",
    "industry": "電機機械",
    "concepts": [
      "電機機械"
    ],
    "close": 38.95,
    "changePercent": 9.87,
    "volume": 7489521,
    "tradeValue": 286841054.0,
    "listedShares": 181473500,
    "turnoverRate": 4.1271,
    "peRatio": 39.74,
    "pbRatio": 1.82,
    "dividendYield": 1.54,
    "revenueMonth": "2026-05",
    "revenueMillion": 422.35,
    "revenueMomPct": 29.81,
    "revenueYoyPct": 8.14,
    "fundamentalScore": 61.3,
    "technicalScore": 70,
    "chipScore": 73.9,
    "turnoverScore": 91.2,
    "totalScore": 71.5,
    "tradeType": "波段",
    "riskLabel": "過熱",
    "updatedAt": "2026-07-04T01:08:05+08:00",
    "dataDate": "2026-07-02",
    "scoreSource": "official_quote_valuation_revenue",
    "rank": 46
  },
  {
    "code": "2436",
    "symbol": "2436",
    "name": "偉詮電",
    "market": "上市",
    "industry": "半導體業",
    "concepts": [
      "半導體業"
    ],
    "close": 76.2,
    "changePercent": 7.48,
    "volume": 5310617,
    "tradeValue": 394382953.0,
    "listedShares": 200093175,
    "turnoverRate": 2.6541,
    "peRatio": 22.61,
    "pbRatio": 3.46,
    "dividendYield": 2.57,
    "revenueMonth": "2026-05",
    "revenueMillion": 397.04,
    "revenueMomPct": 1.68,
    "revenueYoyPct": 26.11,
    "fundamentalScore": 61.9,
    "technicalScore": 70,
    "chipScore": 75.3,
    "turnoverScore": 87.1,
    "totalScore": 71.5,
    "tradeType": "波段",
    "riskLabel": "過熱",
    "updatedAt": "2026-07-04T01:08:05+08:00",
    "dataDate": "2026-07-02",
    "scoreSource": "official_quote_valuation_revenue",
    "rank": 47
  },
  {
    "code": "4526",
    "symbol": "4526",
    "name": "東台",
    "market": "上市",
    "industry": "電機機械",
    "concepts": [
      "電機機械"
    ],
    "close": 42.0,
    "changePercent": 2.07,
    "volume": 12888602,
    "tradeValue": 549764677.0,
    "listedShares": 254826461,
    "turnoverRate": 5.0578,
    "peRatio": 40.38,
    "pbRatio": 2.22,
    "dividendYield": 2.38,
    "revenueMonth": "2026-05",
    "revenueMillion": 627.5,
    "revenueMomPct": 42.7,
    "revenueYoyPct": 49.95,
    "fundamentalScore": 69.7,
    "technicalScore": 58.2,
    "chipScore": 77.2,
    "turnoverScore": 92.1,
    "totalScore": 71.5,
    "tradeType": "中長期",
    "riskLabel": "過熱",
    "updatedAt": "2026-07-04T01:08:05+08:00",
    "dataDate": "2026-07-02",
    "scoreSource": "official_quote_valuation_revenue",
    "rank": 48
  },
  {
    "code": "6409",
    "symbol": "6409",
    "name": "旭隼",
    "market": "上市",
    "industry": "其他電子業",
    "concepts": [
      "其他電子業"
    ],
    "close": 1185.0,
    "changePercent": 4.87,
    "volume": 2418968,
    "tradeValue": 2864673350.0,
    "listedShares": 88253566,
    "turnoverRate": 2.7409,
    "peRatio": 33.94,
    "pbRatio": 10.06,
    "dividendYield": 3.12,
    "revenueMonth": "2026-05",
    "revenueMillion": 1850.13,
    "revenueMomPct": 4.85,
    "revenueYoyPct": 0.28,
    "fundamentalScore": 57.0,
    "technicalScore": 66.6,
    "chipScore": 84.7,
    "turnoverScore": 87.6,
    "totalScore": 71.4,
    "tradeType": "中長期",
    "riskLabel": "正常",
    "updatedAt": "2026-07-04T01:08:05+08:00",
    "dataDate": "2026-07-02",
    "scoreSource": "official_quote_valuation_revenue",
    "rank": 49
  },
  {
    "code": "8464",
    "symbol": "8464",
    "name": "億豐",
    "market": "上市",
    "industry": "居家生活",
    "concepts": [
      "居家生活"
    ],
    "close": 380.5,
    "changePercent": 6.58,
    "volume": 2024462,
    "tradeValue": 746290009.0,
    "listedShares": 293020200,
    "turnoverRate": 0.6909,
    "peRatio": 17.23,
    "pbRatio": 4.09,
    "dividendYield": 4.2,
    "revenueMonth": "2026-05",
    "revenueMillion": 2584.3,
    "revenueMomPct": -1.56,
    "revenueYoyPct": 3.27,
    "fundamentalScore": 62.9,
    "technicalScore": 70,
    "chipScore": 83.2,
    "turnoverScore": 71.4,
    "totalScore": 71.4,
    "tradeType": "波段",
    "riskLabel": "正常",
    "updatedAt": "2026-07-04T01:08:05+08:00",
    "dataDate": "2026-07-02",
    "scoreSource": "official_quote_valuation_revenue",
    "rank": 50
  },
  {
    "code": "4919",
    "symbol": "4919",
    "name": "新唐",
    "market": "上市",
    "industry": "半導體業",
    "concepts": [
      "半導體業"
    ],
    "close": 185.0,
    "changePercent": 9.79,
    "volume": 12604224,
    "tradeValue": 2214205070.0,
    "listedShares": 419765268,
    "turnoverRate": 3.0027,
    "peRatio": null,
    "pbRatio": 5.87,
    "dividendYield": null,
    "revenueMonth": "2026-05",
    "revenueMillion": 2712.66,
    "revenueMomPct": 7.75,
    "revenueYoyPct": 2.09,
    "fundamentalScore": 53.2,
    "technicalScore": 70,
    "chipScore": 84.2,
    "turnoverScore": 88.7,
    "totalScore": 71.3,
    "tradeType": "波段",
    "riskLabel": "過熱",
    "updatedAt": "2026-07-04T01:08:05+08:00",
    "dataDate": "2026-07-02",
    "scoreSource": "official_quote_valuation_revenue",
    "rank": 51
  },
  {
    "code": "2481",
    "symbol": "2481",
    "name": "強茂",
    "market": "上市",
    "industry": "半導體業",
    "concepts": [
      "半導體業"
    ],
    "close": 213.5,
    "changePercent": 9.77,
    "volume": 11757462,
    "tradeValue": 2434240391.0,
    "listedShares": 382114927,
    "turnoverRate": 3.0769,
    "peRatio": 67.78,
    "pbRatio": 5.63,
    "dividendYield": 0.84,
    "revenueMonth": "2026-05",
    "revenueMillion": 1269.31,
    "revenueMomPct": -2.16,
    "revenueYoyPct": 13.66,
    "fundamentalScore": 51.1,
    "technicalScore": 70,
    "chipScore": 85.5,
    "turnoverScore": 88.9,
    "totalScore": 71.0,
    "tradeType": "波段",
    "riskLabel": "過熱",
    "updatedAt": "2026-07-04T01:08:05+08:00",
    "dataDate": "2026-07-02",
    "scoreSource": "official_quote_valuation_revenue",
    "rank": 52
  },
  {
    "code": "3661",
    "symbol": "3661",
    "name": "世芯-KY",
    "market": "上市",
    "industry": "半導體業",
    "concepts": [
      "半導體業"
    ],
    "close": 4895.0,
    "changePercent": 10.0,
    "volume": 4409997,
    "tradeValue": 20401260625.0,
    "listedShares": 82203722,
    "turnoverRate": 5.3647,
    "peRatio": 71.74,
    "pbRatio": 9.25,
    "dividendYield": 0.7,
    "revenueMonth": "2026-05",
    "revenueMillion": 1935.1,
    "revenueMomPct": -9.26,
    "revenueYoyPct": -33.45,
    "fundamentalScore": 43.2,
    "technicalScore": 70,
    "chipScore": 92.5,
    "turnoverScore": 92.5,
    "totalScore": 71.0,
    "tradeType": "波段",
    "riskLabel": "過熱",
    "updatedAt": "2026-07-04T01:08:05+08:00",
    "dataDate": "2026-07-02",
    "scoreSource": "official_quote_valuation_revenue",
    "rank": 53
  },
  {
    "code": "4763",
    "symbol": "4763",
    "name": "材料*-KY",
    "market": "上市",
    "industry": "化學工業",
    "concepts": [
      "化學工業"
    ],
    "close": 49.5,
    "changePercent": 3.34,
    "volume": 18088729,
    "tradeValue": 882003477.0,
    "listedShares": 989146670,
    "turnoverRate": 1.8287,
    "peRatio": 9.57,
    "pbRatio": 2.27,
    "dividendYield": 6.16,
    "revenueMonth": "2026-05",
    "revenueMillion": 952.05,
    "revenueMomPct": 8.48,
    "revenueYoyPct": -22.69,
    "fundamentalScore": 66.2,
    "technicalScore": 62.0,
    "chipScore": 79.7,
    "turnoverScore": 84.1,
    "totalScore": 71.0,
    "tradeType": "中長期",
    "riskLabel": "正常",
    "updatedAt": "2026-07-04T01:08:05+08:00",
    "dataDate": "2026-07-02",
    "scoreSource": "official_quote_valuation_revenue",
    "rank": 54
  },
  {
    "code": "6139",
    "symbol": "6139",
    "name": "亞翔",
    "market": "上市",
    "industry": "其他電子業",
    "concepts": [
      "其他電子業"
    ],
    "close": 939.0,
    "changePercent": 2.96,
    "volume": 4610822,
    "tradeValue": 4292614547.0,
    "listedShares": 235575724,
    "turnoverRate": 1.9573,
    "peRatio": 26.06,
    "pbRatio": 10.1,
    "dividendYield": 2.45,
    "revenueMonth": "2026-05",
    "revenueMillion": 8587.73,
    "revenueMomPct": 0.61,
    "revenueYoyPct": 103.26,
    "fundamentalScore": 62.7,
    "technicalScore": 60.9,
    "chipScore": 85.1,
    "turnoverScore": 84.6,
    "totalScore": 71.0,
    "tradeType": "中長期",
    "riskLabel": "正常",
    "updatedAt": "2026-07-04T01:08:05+08:00",
    "dataDate": "2026-07-02",
    "scoreSource": "official_quote_valuation_revenue",
    "rank": 55
  },
  {
    "code": "6669",
    "symbol": "6669",
    "name": "緯穎",
    "market": "上市",
    "industry": "電腦及週邊設備業",
    "concepts": [
      "電腦及週邊設備業"
    ],
    "close": 5200.0,
    "changePercent": 3.28,
    "volume": 2817565,
    "tradeValue": 14269535045.0,
    "listedShares": 185840791,
    "turnoverRate": 1.5161,
    "peRatio": 17.43,
    "pbRatio": 6.89,
    "dividendYield": 3.16,
    "revenueMonth": "2026-05",
    "revenueMillion": 84050.47,
    "revenueMomPct": 1.59,
    "revenueYoyPct": 18.16,
    "fundamentalScore": 61.4,
    "technicalScore": 61.8,
    "chipScore": 87.1,
    "turnoverScore": 82.1,
    "totalScore": 71.0,
    "tradeType": "中長期",
    "riskLabel": "正常",
    "updatedAt": "2026-07-04T01:08:05+08:00",
    "dataDate": "2026-07-02",
    "scoreSource": "official_quote_valuation_revenue",
    "rank": 56
  },
  {
    "code": "4576",
    "symbol": "4576",
    "name": "大銀微系統",
    "market": "上市",
    "industry": "電機機械",
    "concepts": [
      "電機機械"
    ],
    "close": 235.0,
    "changePercent": 9.81,
    "volume": 2889639,
    "tradeValue": 663324085.0,
    "listedShares": 119801848,
    "turnoverRate": 2.412,
    "peRatio": 92.52,
    "pbRatio": 6.8,
    "dividendYield": 0.34,
    "revenueMonth": "2026-05",
    "revenueMillion": 335.39,
    "revenueMomPct": -1.95,
    "revenueYoyPct": 48.04,
    "fundamentalScore": 55.3,
    "technicalScore": 70,
    "chipScore": 80.5,
    "turnoverScore": 86.4,
    "totalScore": 70.7,
    "tradeType": "波段",
    "riskLabel": "過熱",
    "updatedAt": "2026-07-04T01:08:05+08:00",
    "dataDate": "2026-07-02",
    "scoreSource": "official_quote_valuation_revenue",
    "rank": 57
  },
  {
    "code": "1314",
    "symbol": "1314",
    "name": "中石化",
    "market": "上市",
    "industry": "塑膠工業",
    "concepts": [
      "塑膠工業"
    ],
    "close": 8.99,
    "changePercent": 7.28,
    "volume": 121860999,
    "tradeValue": 1086803863.0,
    "listedShares": 3784850130,
    "turnoverRate": 3.2197,
    "peRatio": null,
    "pbRatio": 0.45,
    "dividendYield": null,
    "revenueMonth": "2026-05",
    "revenueMillion": 1290.22,
    "revenueMomPct": -17.11,
    "revenueYoyPct": -23.83,
    "fundamentalScore": 51.9,
    "technicalScore": 70,
    "chipScore": 82.6,
    "turnoverScore": 89.3,
    "totalScore": 70.6,
    "tradeType": "波段",
    "riskLabel": "過熱",
    "updatedAt": "2026-07-04T01:08:05+08:00",
    "dataDate": "2026-07-02",
    "scoreSource": "official_quote_valuation_revenue",
    "rank": 58
  },
  {
    "code": "2302",
    "symbol": "2302",
    "name": "麗正",
    "market": "上市",
    "industry": "半導體業",
    "concepts": [
      "半導體業"
    ],
    "close": 55.4,
    "changePercent": 9.92,
    "volume": 18216154,
    "tradeValue": 973291177.0,
    "listedShares": 166302881,
    "turnoverRate": 10.9536,
    "peRatio": 70.13,
    "pbRatio": 5.16,
    "dividendYield": 0.63,
    "revenueMonth": "2026-05",
    "revenueMillion": 86.33,
    "revenueMomPct": -12.25,
    "revenueYoyPct": 22.31,
    "fundamentalScore": 50.4,
    "technicalScore": 70,
    "chipScore": 81.7,
    "turnoverScore": 94.0,
    "totalScore": 70.6,
    "tradeType": "波段",
    "riskLabel": "過熱",
    "updatedAt": "2026-07-04T01:08:05+08:00",
    "dataDate": "2026-07-02",
    "scoreSource": "official_quote_valuation_revenue",
    "rank": 59
  },
  {
    "code": "8070",
    "symbol": "8070",
    "name": "長華*",
    "market": "上市",
    "industry": "電子通路業",
    "concepts": [
      "電子通路業"
    ],
    "close": 56.5,
    "changePercent": 5.81,
    "volume": 7113073,
    "tradeValue": 396956997.0,
    "listedShares": 725648455,
    "turnoverRate": 0.9802,
    "peRatio": 53.3,
    "pbRatio": 2.25,
    "dividendYield": 4.8,
    "revenueMonth": "2026-05",
    "revenueMillion": 1973.14,
    "revenueMomPct": -3.7,
    "revenueYoyPct": 26.34,
    "fundamentalScore": 63.0,
    "technicalScore": 69.4,
    "chipScore": 77.4,
    "turnoverScore": 76.6,
    "totalScore": 70.6,
    "tradeType": "波段",
    "riskLabel": "正常",
    "updatedAt": "2026-07-04T01:08:05+08:00",
    "dataDate": "2026-07-02",
    "scoreSource": "official_quote_valuation_revenue",
    "rank": 60
  },
  {
    "code": "2337",
    "symbol": "2337",
    "name": "旺宏",
    "market": "上市",
    "industry": "半導體業",
    "concepts": [
      "半導體業"
    ],
    "close": 145.5,
    "changePercent": 1.39,
    "volume": 71136879,
    "tradeValue": 10089935630.0,
    "listedShares": 1981308820,
    "turnoverRate": 3.5904,
    "peRatio": null,
    "pbRatio": 5.69,
    "dividendYield": null,
    "revenueMonth": "2026-05",
    "revenueMillion": 6255.65,
    "revenueMomPct": 5.8,
    "revenueYoyPct": 175.8,
    "fundamentalScore": 64.5,
    "technicalScore": 56.2,
    "chipScore": 83.2,
    "turnoverScore": 90.2,
    "totalScore": 70.5,
    "tradeType": "中長期",
    "riskLabel": "正常",
    "updatedAt": "2026-07-04T01:08:05+08:00",
    "dataDate": "2026-07-02",
    "scoreSource": "official_quote_valuation_revenue",
    "rank": 61
  },
  {
    "code": "3017",
    "symbol": "3017",
    "name": "奇鋐",
    "market": "上市",
    "industry": "電腦及週邊設備業",
    "concepts": [
      "電腦及週邊設備業"
    ],
    "close": 2740.0,
    "changePercent": 4.58,
    "volume": 5061323,
    "tradeValue": 13521473385.0,
    "listedShares": 392543007,
    "turnoverRate": 1.2894,
    "peRatio": 45.02,
    "pbRatio": 23.81,
    "dividendYield": 0.77,
    "revenueMonth": "2026-05",
    "revenueMillion": 15871.4,
    "revenueMomPct": 1.54,
    "revenueYoyPct": 60.64,
    "fundamentalScore": 57.1,
    "technicalScore": 65.7,
    "chipScore": 86.5,
    "turnoverScore": 80.1,
    "totalScore": 70.5,
    "tradeType": "中長期",
    "riskLabel": "正常",
    "updatedAt": "2026-07-04T01:08:05+08:00",
    "dataDate": "2026-07-02",
    "scoreSource": "official_quote_valuation_revenue",
    "rank": 62
  },
  {
    "code": "1303",
    "symbol": "1303",
    "name": "南亞",
    "market": "上市",
    "industry": "塑膠工業",
    "concepts": [
      "塑膠工業"
    ],
    "close": 197.0,
    "changePercent": 7.65,
    "volume": 52721361,
    "tradeValue": 10007829188.0,
    "listedShares": 7930821589,
    "turnoverRate": 0.6648,
    "peRatio": 85.28,
    "pbRatio": 4.07,
    "dividendYield": 0.41,
    "revenueMonth": "2026-05",
    "revenueMillion": 28830.98,
    "revenueMomPct": 4.15,
    "revenueYoyPct": 31.35,
    "fundamentalScore": 56.6,
    "technicalScore": 70,
    "chipScore": 87.3,
    "turnoverScore": 70.6,
    "totalScore": 70.4,
    "tradeType": "波段",
    "riskLabel": "過熱",
    "updatedAt": "2026-07-04T01:08:05+08:00",
    "dataDate": "2026-07-02",
    "scoreSource": "official_quote_valuation_revenue",
    "rank": 63
  },
  {
    "code": "6831",
    "symbol": "6831",
    "name": "邁科",
    "market": "上市",
    "industry": "電腦及週邊設備業",
    "concepts": [
      "電腦及週邊設備業"
    ],
    "close": 956.0,
    "changePercent": 5.87,
    "volume": 1847184,
    "tradeValue": 1754615079.0,
    "listedShares": 67500000,
    "turnoverRate": 2.7366,
    "peRatio": 194.31,
    "pbRatio": 24.12,
    "dividendYield": 0.31,
    "revenueMonth": "2026-05",
    "revenueMillion": 330.27,
    "revenueMomPct": 54.97,
    "revenueYoyPct": -10.76,
    "fundamentalScore": 53.5,
    "technicalScore": 69.6,
    "chipScore": 81.5,
    "turnoverScore": 87.6,
    "totalScore": 70.4,
    "tradeType": "波段",
    "riskLabel": "正常",
    "updatedAt": "2026-07-04T01:08:05+08:00",
    "dataDate": "2026-07-02",
    "scoreSource": "official_quote_valuation_revenue",
    "rank": 64
  },
  {
    "code": "1714",
    "symbol": "1714",
    "name": "和桐",
    "market": "上市",
    "industry": "化學工業",
    "concepts": [
      "化學工業"
    ],
    "close": 20.7,
    "changePercent": 7.25,
    "volume": 10325115,
    "tradeValue": 210020998.0,
    "listedShares": 991824808,
    "turnoverRate": 1.041,
    "peRatio": 32.34,
    "pbRatio": 1.59,
    "dividendYield": 0.87,
    "revenueMonth": "2026-05",
    "revenueMillion": 3477.94,
    "revenueMomPct": 9.24,
    "revenueYoyPct": 84.85,
    "fundamentalScore": 66.7,
    "technicalScore": 70,
    "chipScore": 70.4,
    "turnoverScore": 77.5,
    "totalScore": 70.2,
    "tradeType": "波段",
    "riskLabel": "過熱",
    "updatedAt": "2026-07-04T01:08:05+08:00",
    "dataDate": "2026-07-02",
    "scoreSource": "official_quote_valuation_revenue",
    "rank": 65
  },
  {
    "code": "5484",
    "symbol": "5484",
    "name": "慧友",
    "market": "上市",
    "industry": "光電業",
    "concepts": [
      "光電業"
    ],
    "close": 49.4,
    "changePercent": 9.9,
    "volume": 1063734,
    "tradeValue": 51621213.0,
    "listedShares": 66801000,
    "turnoverRate": 1.5924,
    "peRatio": 133.51,
    "pbRatio": 6.4,
    "dividendYield": null,
    "revenueMonth": "2026-05",
    "revenueMillion": 80.91,
    "revenueMomPct": 50.33,
    "revenueYoyPct": 152.32,
    "fundamentalScore": 66.2,
    "technicalScore": 70,
    "chipScore": 68.1,
    "turnoverScore": 82.4,
    "totalScore": 70.2,
    "tradeType": "波段",
    "riskLabel": "過熱",
    "updatedAt": "2026-07-04T01:08:05+08:00",
    "dataDate": "2026-07-02",
    "scoreSource": "official_quote_valuation_revenue",
    "rank": 66
  },
  {
    "code": "6937",
    "symbol": "6937",
    "name": "天虹",
    "market": "上市",
    "industry": "半導體業",
    "concepts": [
      "半導體業"
    ],
    "close": 291.5,
    "changePercent": 7.56,
    "volume": 1080288,
    "tradeValue": 311203132.0,
    "listedShares": 67655263,
    "turnoverRate": 1.5968,
    "peRatio": 89.97,
    "pbRatio": 5.73,
    "dividendYield": 0.48,
    "revenueMonth": "2026-05",
    "revenueMillion": 190.8,
    "revenueMomPct": 24.53,
    "revenueYoyPct": 19.92,
    "fundamentalScore": 55.8,
    "technicalScore": 70,
    "chipScore": 80.2,
    "turnoverScore": 82.5,
    "totalScore": 70.2,
    "tradeType": "波段",
    "riskLabel": "過熱",
    "updatedAt": "2026-07-04T01:08:05+08:00",
    "dataDate": "2026-07-02",
    "scoreSource": "official_quote_valuation_revenue",
    "rank": 67
  },
  {
    "code": "6202",
    "symbol": "6202",
    "name": "盛群",
    "market": "上市",
    "industry": "半導體業",
    "concepts": [
      "半導體業"
    ],
    "close": 69.9,
    "changePercent": 8.54,
    "volume": 8582927,
    "tradeValue": 585489567.0,
    "listedShares": 230388200,
    "turnoverRate": 3.7254,
    "peRatio": 105.91,
    "pbRatio": 3.99,
    "dividendYield": 0.97,
    "revenueMonth": "2026-05",
    "revenueMillion": 312.54,
    "revenueMomPct": -1.9,
    "revenueYoyPct": 6.63,
    "fundamentalScore": 53.0,
    "technicalScore": 70,
    "chipScore": 78.4,
    "turnoverScore": 90.6,
    "totalScore": 70.1,
    "tradeType": "波段",
    "riskLabel": "過熱",
    "updatedAt": "2026-07-04T01:08:05+08:00",
    "dataDate": "2026-07-02",
    "scoreSource": "official_quote_valuation_revenue",
    "rank": 68
  },
  {
    "code": "2449",
    "symbol": "2449",
    "name": "京元電子",
    "market": "上市",
    "industry": "半導體業",
    "concepts": [
      "半導體業"
    ],
    "close": 347.5,
    "changePercent": 4.98,
    "volume": 24008391,
    "tradeValue": 8048260310.0,
    "listedShares": 1222745065,
    "turnoverRate": 1.9635,
    "peRatio": 47.15,
    "pbRatio": 7.81,
    "dividendYield": 0.43,
    "revenueMonth": "2026-05",
    "revenueMillion": 3776.93,
    "revenueMomPct": 0.91,
    "revenueYoyPct": 36.61,
    "fundamentalScore": 54.3,
    "technicalScore": 66.9,
    "chipScore": 83.8,
    "turnoverScore": 84.6,
    "totalScore": 70.0,
    "tradeType": "中長期",
    "riskLabel": "正常",
    "updatedAt": "2026-07-04T01:08:05+08:00",
    "dataDate": "2026-07-02",
    "scoreSource": "official_quote_valuation_revenue",
    "rank": 69
  },
  {
    "code": "1210",
    "symbol": "1210",
    "name": "大成",
    "market": "上市",
    "industry": "食品工業",
    "concepts": [
      "食品工業"
    ],
    "close": 57.6,
    "changePercent": 3.23,
    "volume": 7098772,
    "tradeValue": 404777539.0,
    "listedShares": 894767222,
    "turnoverRate": 0.7934,
    "peRatio": 13.65,
    "pbRatio": 1.92,
    "dividendYield": 5.21,
    "revenueMonth": "2026-05",
    "revenueMillion": 9065.7,
    "revenueMomPct": -0.36,
    "revenueYoyPct": 10.16,
    "fundamentalScore": 67.7,
    "technicalScore": 61.7,
    "chipScore": 80.1,
    "turnoverScore": 73.7,
    "totalScore": 69.9,
    "tradeType": "中長期",
    "riskLabel": "正常",
    "updatedAt": "2026-07-04T01:08:05+08:00",
    "dataDate": "2026-07-02",
    "scoreSource": "official_quote_valuation_revenue",
    "rank": 70
  },
  {
    "code": "2451",
    "symbol": "2451",
    "name": "創見",
    "market": "上市",
    "industry": "半導體業",
    "concepts": [
      "半導體業"
    ],
    "close": 258.0,
    "changePercent": 2.99,
    "volume": 4452155,
    "tradeValue": 1119383765.0,
    "listedShares": 431345675,
    "turnoverRate": 1.0322,
    "peRatio": 8.34,
    "pbRatio": 4.24,
    "dividendYield": 4.57,
    "revenueMonth": "2026-05",
    "revenueMillion": 6297.95,
    "revenueMomPct": -15.46,
    "revenueYoyPct": 469.83,
    "fundamentalScore": 69.7,
    "technicalScore": 61.0,
    "chipScore": 76.2,
    "turnoverScore": 77.4,
    "totalScore": 69.9,
    "tradeType": "中長期",
    "riskLabel": "正常",
    "updatedAt": "2026-07-04T01:08:05+08:00",
    "dataDate": "2026-07-02",
    "scoreSource": "official_quote_valuation_revenue",
    "rank": 71
  },
  {
    "code": "8081",
    "symbol": "8081",
    "name": "致新",
    "market": "上市",
    "industry": "半導體業",
    "concepts": [
      "半導體業"
    ],
    "close": 316.0,
    "changePercent": 0.0,
    "volume": 4601189,
    "tradeValue": 1401204975.0,
    "listedShares": 86172072,
    "turnoverRate": 5.3395,
    "peRatio": 17.99,
    "pbRatio": 3.74,
    "dividendYield": 5.06,
    "revenueMonth": "2026-05",
    "revenueMillion": 748.7,
    "revenueMomPct": 0.42,
    "revenueYoyPct": -3.28,
    "fundamentalScore": 63.5,
    "technicalScore": 52.0,
    "chipScore": 85.7,
    "turnoverScore": 92.4,
    "totalScore": 69.9,
    "tradeType": "中長期",
    "riskLabel": "過熱",
    "updatedAt": "2026-07-04T01:08:05+08:00",
    "dataDate": "2026-07-02",
    "scoreSource": "official_quote_valuation_revenue",
    "rank": 72
  },
  {
    "code": "1313",
    "symbol": "1313",
    "name": "聯成",
    "market": "上市",
    "industry": "塑膠工業",
    "concepts": [
      "塑膠工業"
    ],
    "close": 13.0,
    "changePercent": 6.56,
    "volume": 17611433,
    "tradeValue": 225372393.0,
    "listedShares": 1330846107,
    "turnoverRate": 1.3233,
    "peRatio": null,
    "pbRatio": 0.6,
    "dividendYield": 0.77,
    "revenueMonth": "2026-05",
    "revenueMillion": 5371.03,
    "revenueMomPct": -8.64,
    "revenueYoyPct": 4.71,
    "fundamentalScore": 58.2,
    "technicalScore": 70,
    "chipScore": 76.8,
    "turnoverScore": 80.7,
    "totalScore": 69.8,
    "tradeType": "波段",
    "riskLabel": "正常",
    "updatedAt": "2026-07-04T01:08:05+08:00",
    "dataDate": "2026-07-02",
    "scoreSource": "official_quote_valuation_revenue",
    "rank": 73
  },
  {
    "code": "3036",
    "symbol": "3036",
    "name": "文曄",
    "market": "上市",
    "industry": "電子通路業",
    "concepts": [
      "電子通路業"
    ],
    "close": 217.5,
    "changePercent": 3.08,
    "volume": 8637249,
    "tradeValue": 1859418480.0,
    "listedShares": 1269148301,
    "turnoverRate": 0.6806,
    "peRatio": 15.43,
    "pbRatio": 2.44,
    "dividendYield": 3.59,
    "revenueMonth": "2026-05",
    "revenueMillion": 197924.57,
    "revenueMomPct": -6.21,
    "revenueYoyPct": 152.69,
    "fundamentalScore": 70.4,
    "technicalScore": 61.2,
    "chipScore": 78.6,
    "turnoverScore": 70.9,
    "totalScore": 69.8,
    "tradeType": "中長期",
    "riskLabel": "正常",
    "updatedAt": "2026-07-04T01:08:05+08:00",
    "dataDate": "2026-07-02",
    "scoreSource": "official_quote_valuation_revenue",
    "rank": 74
  },
  {
    "code": "6770",
    "symbol": "6770",
    "name": "力積電",
    "market": "上市",
    "industry": "半導體業",
    "concepts": [
      "半導體業"
    ],
    "close": 74.7,
    "changePercent": 0.54,
    "volume": 155504558,
    "tradeValue": 11443165955.0,
    "listedShares": 4663803715,
    "turnoverRate": 3.3343,
    "peRatio": 42.2,
    "pbRatio": 3.28,
    "dividendYield": null,
    "revenueMonth": "2026-05",
    "revenueMillion": 5770.37,
    "revenueMomPct": 14.36,
    "revenueYoyPct": 58.86,
    "fundamentalScore": 64.6,
    "technicalScore": 53.6,
    "chipScore": 83.7,
    "turnoverScore": 89.6,
    "totalScore": 69.8,
    "tradeType": "中長期",
    "riskLabel": "正常",
    "updatedAt": "2026-07-04T01:08:05+08:00",
    "dataDate": "2026-07-02",
    "scoreSource": "official_quote_valuation_revenue",
    "rank": 75
  },
  {
    "code": "4720",
    "symbol": "4720",
    "name": "德淵",
    "market": "上市",
    "industry": "化學工業",
    "concepts": [
      "化學工業"
    ],
    "close": 25.95,
    "changePercent": 7.45,
    "volume": 5189071,
    "tradeValue": 133068757.0,
    "listedShares": 114516037,
    "turnoverRate": 4.5313,
    "peRatio": 42.54,
    "pbRatio": 1.83,
    "dividendYield": 1.54,
    "revenueMonth": "2026-05",
    "revenueMillion": 331.3,
    "revenueMomPct": -8.79,
    "revenueYoyPct": 15.22,
    "fundamentalScore": 56.1,
    "technicalScore": 70,
    "chipScore": 72.4,
    "turnoverScore": 91.7,
    "totalScore": 69.7,
    "tradeType": "波段",
    "riskLabel": "過熱",
    "updatedAt": "2026-07-04T01:08:05+08:00",
    "dataDate": "2026-07-02",
    "scoreSource": "official_quote_valuation_revenue",
    "rank": 76
  },
  {
    "code": "9945",
    "symbol": "9945",
    "name": "潤泰新",
    "market": "上市",
    "industry": "其他業",
    "concepts": [
      "其他業"
    ],
    "close": 26.65,
    "changePercent": 0.19,
    "volume": 16665724,
    "tradeValue": 443483743.0,
    "listedShares": 2844225086,
    "turnoverRate": 0.5859,
    "peRatio": 7.49,
    "pbRatio": 0.66,
    "dividendYield": 4.13,
    "revenueMonth": "2026-05",
    "revenueMillion": 5231.8,
    "revenueMomPct": 32.83,
    "revenueYoyPct": 72.0,
    "fundamentalScore": 81.0,
    "technicalScore": 52.6,
    "chipScore": 77.2,
    "turnoverScore": 68.8,
    "totalScore": 69.7,
    "tradeType": "中長期",
    "riskLabel": "正常",
    "updatedAt": "2026-07-04T01:08:05+08:00",
    "dataDate": "2026-07-02",
    "scoreSource": "official_quote_valuation_revenue",
    "rank": 77
  },
  {
    "code": "2313",
    "symbol": "2313",
    "name": "華通",
    "market": "上市",
    "industry": "電子零組件業",
    "concepts": [
      "電子零組件業"
    ],
    "close": 228.5,
    "changePercent": 3.86,
    "volume": 29171042,
    "tradeValue": 6431305557.0,
    "listedShares": 1191820589,
    "turnoverRate": 2.4476,
    "peRatio": 40.3,
    "pbRatio": 5.81,
    "dividendYield": 1.23,
    "revenueMonth": "2026-05",
    "revenueMillion": 6761.66,
    "revenueMomPct": 7.07,
    "revenueYoyPct": 13.02,
    "fundamentalScore": 53.1,
    "technicalScore": 63.6,
    "chipScore": 86.5,
    "turnoverScore": 86.5,
    "totalScore": 69.6,
    "tradeType": "中長期",
    "riskLabel": "正常",
    "updatedAt": "2026-07-04T01:08:05+08:00",
    "dataDate": "2026-07-02",
    "scoreSource": "official_quote_valuation_revenue",
    "rank": 78
  },
  {
    "code": "5285",
    "symbol": "5285",
    "name": "界霖",
    "market": "上市",
    "industry": "半導體業",
    "concepts": [
      "半導體業"
    ],
    "close": 99.4,
    "changePercent": 7.0,
    "volume": 3982716,
    "tradeValue": 389223103.0,
    "listedShares": 102040926,
    "turnoverRate": 3.9031,
    "peRatio": 47.33,
    "pbRatio": 3.41,
    "dividendYield": 1.51,
    "revenueMonth": "2026-05",
    "revenueMillion": 522.2,
    "revenueMomPct": -10.29,
    "revenueYoyPct": 18.5,
    "fundamentalScore": 54.1,
    "technicalScore": 70,
    "chipScore": 74.8,
    "turnoverScore": 91.0,
    "totalScore": 69.6,
    "tradeType": "波段",
    "riskLabel": "過熱",
    "updatedAt": "2026-07-04T01:08:05+08:00",
    "dataDate": "2026-07-02",
    "scoreSource": "official_quote_valuation_revenue",
    "rank": 79
  },
  {
    "code": "6505",
    "symbol": "6505",
    "name": "台塑化",
    "market": "上市",
    "industry": "油電燃氣業",
    "concepts": [
      "油電燃氣業"
    ],
    "close": 57.6,
    "changePercent": 7.46,
    "volume": 24282487,
    "tradeValue": 1366392281.0,
    "listedShares": 9525959652,
    "turnoverRate": 0.2549,
    "peRatio": 20.65,
    "pbRatio": 1.46,
    "dividendYield": 2.08,
    "revenueMonth": "2026-05",
    "revenueMillion": 57777.22,
    "revenueMomPct": -6.09,
    "revenueYoyPct": 26.87,
    "fundamentalScore": 62.3,
    "technicalScore": 70,
    "chipScore": 87.4,
    "turnoverScore": 53.6,
    "totalScore": 69.6,
    "tradeType": "波段",
    "riskLabel": "過熱",
    "updatedAt": "2026-07-04T01:08:05+08:00",
    "dataDate": "2026-07-02",
    "scoreSource": "official_quote_valuation_revenue",
    "rank": 80
  },
  {
    "code": "8103",
    "symbol": "8103",
    "name": "瀚荃",
    "market": "上市",
    "industry": "電子零組件業",
    "concepts": [
      "電子零組件業"
    ],
    "close": 105.0,
    "changePercent": 5.63,
    "volume": 1686574,
    "tradeValue": 174253683.0,
    "listedShares": 78436671,
    "turnoverRate": 2.1502,
    "peRatio": 22.63,
    "pbRatio": 2.13,
    "dividendYield": 2.67,
    "revenueMonth": "2026-05",
    "revenueMillion": 349.97,
    "revenueMomPct": -5.89,
    "revenueYoyPct": 22.36,
    "fundamentalScore": 62.5,
    "technicalScore": 68.9,
    "chipScore": 69.6,
    "turnoverScore": 85.5,
    "totalScore": 69.6,
    "tradeType": "波段",
    "riskLabel": "正常",
    "updatedAt": "2026-07-04T01:08:05+08:00",
    "dataDate": "2026-07-02",
    "scoreSource": "official_quote_valuation_revenue",
    "rank": 81
  },
  {
    "code": "9939",
    "symbol": "9939",
    "name": "宏全",
    "market": "上市",
    "industry": "其他業",
    "concepts": [
      "其他業"
    ],
    "close": 118.0,
    "changePercent": 0.0,
    "volume": 6358714,
    "tradeValue": 749268652.0,
    "listedShares": 295786475,
    "turnoverRate": 2.1498,
    "peRatio": 13.08,
    "pbRatio": 1.84,
    "dividendYield": 5.25,
    "revenueMonth": "2026-05",
    "revenueMillion": 2880.32,
    "revenueMomPct": 3.36,
    "revenueYoyPct": 10.81,
    "fundamentalScore": 68.4,
    "technicalScore": 52.0,
    "chipScore": 82.5,
    "turnoverScore": 85.5,
    "totalScore": 69.6,
    "tradeType": "中長期",
    "riskLabel": "正常",
    "updatedAt": "2026-07-04T01:08:05+08:00",
    "dataDate": "2026-07-02",
    "scoreSource": "official_quote_valuation_revenue",
    "rank": 82
  },
  {
    "code": "2250",
    "symbol": "2250",
    "name": "IKKA-KY",
    "market": "上市",
    "industry": "汽車工業",
    "concepts": [
      "汽車工業"
    ],
    "close": 75.4,
    "changePercent": 9.91,
    "volume": 1255105,
    "tradeValue": 93224972.0,
    "listedShares": 36388226,
    "turnoverRate": 3.4492,
    "peRatio": 22.37,
    "pbRatio": 1.28,
    "dividendYield": 3.98,
    "revenueMonth": "2026-05",
    "revenueMillion": 230.88,
    "revenueMomPct": -17.42,
    "revenueYoyPct": -15.38,
    "fundamentalScore": 57.2,
    "technicalScore": 70,
    "chipScore": 71.4,
    "turnoverScore": 89.7,
    "totalScore": 69.5,
    "tradeType": "波段",
    "riskLabel": "過熱",
    "updatedAt": "2026-07-04T01:08:05+08:00",
    "dataDate": "2026-07-02",
    "scoreSource": "official_quote_valuation_revenue",
    "rank": 83
  },
  {
    "code": "3346",
    "symbol": "3346",
    "name": "麗清",
    "market": "上市",
    "industry": "汽車工業",
    "concepts": [
      "汽車工業"
    ],
    "close": 29.3,
    "changePercent": 9.94,
    "volume": 5117513,
    "tradeValue": 146023306.0,
    "listedShares": 121228352,
    "turnoverRate": 4.2214,
    "peRatio": null,
    "pbRatio": 0.99,
    "dividendYield": 0.38,
    "revenueMonth": "2026-05",
    "revenueMillion": 732.33,
    "revenueMomPct": 6.63,
    "revenueYoyPct": -2.52,
    "fundamentalScore": 59.3,
    "technicalScore": 70,
    "chipScore": 68.0,
    "turnoverScore": 91.2,
    "totalScore": 69.5,
    "tradeType": "波段",
    "riskLabel": "過熱",
    "updatedAt": "2026-07-04T01:08:05+08:00",
    "dataDate": "2026-07-02",
    "scoreSource": "official_quote_valuation_revenue",
    "rank": 84
  },
  {
    "code": "1718",
    "symbol": "1718",
    "name": "中纖",
    "market": "上市",
    "industry": "化學工業",
    "concepts": [
      "化學工業"
    ],
    "close": 13.6,
    "changePercent": 9.68,
    "volume": 63746998,
    "tradeValue": 852237434.0,
    "listedShares": 1685905745,
    "turnoverRate": 3.7812,
    "peRatio": 56.67,
    "pbRatio": 0.81,
    "dividendYield": null,
    "revenueMonth": "2026-05",
    "revenueMillion": 3777.93,
    "revenueMomPct": -15.02,
    "revenueYoyPct": 9.14,
    "fundamentalScore": 56.3,
    "technicalScore": 70,
    "chipScore": 71.5,
    "turnoverScore": 90.8,
    "totalScore": 69.4,
    "tradeType": "波段",
    "riskLabel": "過熱",
    "updatedAt": "2026-07-04T01:08:05+08:00",
    "dataDate": "2026-07-02",
    "scoreSource": "official_quote_valuation_revenue",
    "rank": 85
  },
  {
    "code": "5269",
    "symbol": "5269",
    "name": "祥碩",
    "market": "上市",
    "industry": "半導體業",
    "concepts": [
      "半導體業"
    ],
    "close": 1520.0,
    "changePercent": 3.4,
    "volume": 1599190,
    "tradeValue": 2426427505.0,
    "listedShares": 74156679,
    "turnoverRate": 2.1565,
    "peRatio": 18.65,
    "pbRatio": 3.05,
    "dividendYield": 2.96,
    "revenueMonth": "2026-05",
    "revenueMillion": 896.67,
    "revenueMomPct": -6.47,
    "revenueYoyPct": -19.4,
    "fundamentalScore": 57.2,
    "technicalScore": 62.2,
    "chipScore": 82.8,
    "turnoverScore": 85.6,
    "totalScore": 69.4,
    "tradeType": "中長期",
    "riskLabel": "正常",
    "updatedAt": "2026-07-04T01:08:05+08:00",
    "dataDate": "2026-07-02",
    "scoreSource": "official_quote_valuation_revenue",
    "rank": 86
  },
  {
    "code": "3029",
    "symbol": "3029",
    "name": "零壹",
    "market": "上市",
    "industry": "資訊服務業",
    "concepts": [
      "資訊服務業"
    ],
    "close": 102.0,
    "changePercent": 2.82,
    "volume": 2095288,
    "tradeValue": 213564753.0,
    "listedShares": 167005212,
    "turnoverRate": 1.2546,
    "peRatio": 15.0,
    "pbRatio": 3.36,
    "dividendYield": 5.39,
    "revenueMonth": "2026-05",
    "revenueMillion": 2340.24,
    "revenueMomPct": -1.06,
    "revenueYoyPct": 27.41,
    "fundamentalScore": 67.9,
    "technicalScore": 60.5,
    "chipScore": 75.2,
    "turnoverScore": 80.0,
    "totalScore": 69.3,
    "tradeType": "中長期",
    "riskLabel": "正常",
    "updatedAt": "2026-07-04T01:08:05+08:00",
    "dataDate": "2026-07-02",
    "scoreSource": "official_quote_valuation_revenue",
    "rank": 87
  },
  {
    "code": "6235",
    "symbol": "6235",
    "name": "華孚",
    "market": "上市",
    "industry": "電腦及週邊設備業",
    "concepts": [
      "電腦及週邊設備業"
    ],
    "close": 41.55,
    "changePercent": 5.86,
    "volume": 2142980,
    "tradeValue": 88562345.0,
    "listedShares": 199906306,
    "turnoverRate": 1.072,
    "peRatio": 16.04,
    "pbRatio": 1.67,
    "dividendYield": 2.89,
    "revenueMonth": "2026-05",
    "revenueMillion": 523.9,
    "revenueMomPct": 1.07,
    "revenueYoyPct": -1.55,
    "fundamentalScore": 63.0,
    "technicalScore": 69.6,
    "chipScore": 71.0,
    "turnoverScore": 78.0,
    "totalScore": 69.2,
    "tradeType": "波段",
    "riskLabel": "正常",
    "updatedAt": "2026-07-04T01:08:05+08:00",
    "dataDate": "2026-07-02",
    "scoreSource": "official_quote_valuation_revenue",
    "rank": 88
  },
  {
    "code": "6719",
    "symbol": "6719",
    "name": "力智",
    "market": "上市",
    "industry": "半導體業",
    "concepts": [
      "半導體業"
    ],
    "close": 300.0,
    "changePercent": 1.01,
    "volume": 17525994,
    "tradeValue": 5430363426.0,
    "listedShares": 105483989,
    "turnoverRate": 16.6148,
    "peRatio": 41.78,
    "pbRatio": 2.21,
    "dividendYield": 1.53,
    "revenueMonth": "2026-05",
    "revenueMillion": 367.02,
    "revenueMomPct": -4.18,
    "revenueYoyPct": -9.58,
    "fundamentalScore": 53.3,
    "technicalScore": 55.0,
    "chipScore": 90.4,
    "turnoverScore": 94.3,
    "totalScore": 69.2,
    "tradeType": "中長期",
    "riskLabel": "過熱",
    "updatedAt": "2026-07-04T01:08:05+08:00",
    "dataDate": "2026-07-02",
    "scoreSource": "official_quote_valuation_revenue",
    "rank": 89
  },
  {
    "code": "1102",
    "symbol": "1102",
    "name": "亞泥",
    "market": "上市",
    "industry": "水泥工業",
    "concepts": [
      "水泥工業"
    ],
    "close": 36.4,
    "changePercent": 3.7,
    "volume": 25149252,
    "tradeValue": 906041243.0,
    "listedShares": 3546562881,
    "turnoverRate": 0.7091,
    "peRatio": 12.21,
    "pbRatio": 0.73,
    "dividendYield": 6.32,
    "revenueMonth": "2026-05",
    "revenueMillion": 6296.53,
    "revenueMomPct": 10.57,
    "revenueYoyPct": -1.16,
    "fundamentalScore": 69.9,
    "technicalScore": 63.1,
    "chipScore": 72.8,
    "turnoverScore": 71.8,
    "totalScore": 68.9,
    "tradeType": "中長期",
    "riskLabel": "正常",
    "updatedAt": "2026-07-04T01:08:05+08:00",
    "dataDate": "2026-07-02",
    "scoreSource": "official_quote_valuation_revenue",
    "rank": 90
  },
  {
    "code": "3518",
    "symbol": "3518",
    "name": "柏騰",
    "market": "上市",
    "industry": "其他電子業",
    "concepts": [
      "其他電子業"
    ],
    "close": 33.35,
    "changePercent": 9.7,
    "volume": 2536212,
    "tradeValue": 82459652.0,
    "listedShares": 102467230,
    "turnoverRate": 2.4751,
    "peRatio": 15.23,
    "pbRatio": 2.01,
    "dividendYield": null,
    "revenueMonth": "2026-05",
    "revenueMillion": 18.5,
    "revenueMomPct": 2.54,
    "revenueYoyPct": -32.28,
    "fundamentalScore": 57.4,
    "technicalScore": 70,
    "chipScore": 70.6,
    "turnoverScore": 86.7,
    "totalScore": 68.9,
    "tradeType": "波段",
    "riskLabel": "過熱",
    "updatedAt": "2026-07-04T01:08:05+08:00",
    "dataDate": "2026-07-02",
    "scoreSource": "official_quote_valuation_revenue",
    "rank": 91
  },
  {
    "code": "5471",
    "symbol": "5471",
    "name": "松翰",
    "market": "上市",
    "industry": "半導體業",
    "concepts": [
      "半導體業"
    ],
    "close": 63.5,
    "changePercent": 6.19,
    "volume": 4311175,
    "tradeValue": 269767242.0,
    "listedShares": 167877062,
    "turnoverRate": 2.5681,
    "peRatio": 65.46,
    "pbRatio": 3.0,
    "dividendYield": 1.26,
    "revenueMonth": "2026-05",
    "revenueMillion": 301.14,
    "revenueMomPct": -8.32,
    "revenueYoyPct": 27.34,
    "fundamentalScore": 55.3,
    "technicalScore": 70,
    "chipScore": 72.9,
    "turnoverScore": 86.9,
    "totalScore": 68.9,
    "tradeType": "波段",
    "riskLabel": "正常",
    "updatedAt": "2026-07-04T01:08:05+08:00",
    "dataDate": "2026-07-02",
    "scoreSource": "official_quote_valuation_revenue",
    "rank": 92
  },
  {
    "code": "1342",
    "symbol": "1342",
    "name": "八貫",
    "market": "上市",
    "industry": "其他業",
    "concepts": [
      "其他業"
    ],
    "close": 113.5,
    "changePercent": 5.58,
    "volume": 854033,
    "tradeValue": 94904667.0,
    "listedShares": 78000902,
    "turnoverRate": 1.0949,
    "peRatio": 19.08,
    "pbRatio": 4.23,
    "dividendYield": 5.29,
    "revenueMonth": "2026-05",
    "revenueMillion": 337.47,
    "revenueMomPct": -3.38,
    "revenueYoyPct": 37.2,
    "fundamentalScore": 68.9,
    "technicalScore": 68.7,
    "chipScore": 63.1,
    "turnoverScore": 78.4,
    "totalScore": 68.8,
    "tradeType": "波段",
    "riskLabel": "正常",
    "updatedAt": "2026-07-04T01:08:05+08:00",
    "dataDate": "2026-07-02",
    "scoreSource": "official_quote_valuation_revenue",
    "rank": 93
  },
  {
    "code": "2426",
    "symbol": "2426",
    "name": "鼎元",
    "market": "上市",
    "industry": "光電業",
    "concepts": [
      "光電業"
    ],
    "close": 74.8,
    "changePercent": 3.74,
    "volume": 14558340,
    "tradeValue": 1094960625.0,
    "listedShares": 300622252,
    "turnoverRate": 4.8427,
    "peRatio": null,
    "pbRatio": 5.98,
    "dividendYield": 0.13,
    "revenueMonth": "2026-05",
    "revenueMillion": 233.36,
    "revenueMomPct": 11.39,
    "revenueYoyPct": 3.12,
    "fundamentalScore": 52.3,
    "technicalScore": 63.2,
    "chipScore": 81.5,
    "turnoverScore": 91.9,
    "totalScore": 68.8,
    "tradeType": "中長期",
    "riskLabel": "正常",
    "updatedAt": "2026-07-04T01:08:05+08:00",
    "dataDate": "2026-07-02",
    "scoreSource": "official_quote_valuation_revenue",
    "rank": 94
  },
  {
    "code": "2610",
    "symbol": "2610",
    "name": "華航",
    "market": "上市",
    "industry": "航運業",
    "concepts": [
      "航運業"
    ],
    "close": 22.85,
    "changePercent": 1.33,
    "volume": 59763252,
    "tradeValue": 1355431277.0,
    "listedShares": 6119964937,
    "turnoverRate": 0.9765,
    "peRatio": 8.93,
    "pbRatio": 1.36,
    "dividendYield": 3.54,
    "revenueMonth": "2026-05",
    "revenueMillion": 21229.73,
    "revenueMomPct": 1.8,
    "revenueYoyPct": 27.73,
    "fundamentalScore": 69.7,
    "technicalScore": 56.0,
    "chipScore": 78.3,
    "turnoverScore": 76.5,
    "totalScore": 68.8,
    "tradeType": "中長期",
    "riskLabel": "正常",
    "updatedAt": "2026-07-04T01:08:05+08:00",
    "dataDate": "2026-07-02",
    "scoreSource": "official_quote_valuation_revenue",
    "rank": 95
  },
  {
    "code": "5469",
    "symbol": "5469",
    "name": "瀚宇博",
    "market": "上市",
    "industry": "電子零組件業",
    "concepts": [
      "電子零組件業"
    ],
    "close": 87.5,
    "changePercent": 1.04,
    "volume": 8858041,
    "tradeValue": 778668960.0,
    "listedShares": 486166000,
    "turnoverRate": 1.822,
    "peRatio": 15.27,
    "pbRatio": 1.13,
    "dividendYield": 2.88,
    "revenueMonth": "2026-05",
    "revenueMillion": 5591.84,
    "revenueMomPct": 3.42,
    "revenueYoyPct": 3.6,
    "fundamentalScore": 66.1,
    "technicalScore": 55.1,
    "chipScore": 79.2,
    "turnoverScore": 84.1,
    "totalScore": 68.8,
    "tradeType": "中長期",
    "riskLabel": "正常",
    "updatedAt": "2026-07-04T01:08:05+08:00",
    "dataDate": "2026-07-02",
    "scoreSource": "official_quote_valuation_revenue",
    "rank": 96
  },
  {
    "code": "4585",
    "symbol": "4585",
    "name": "達明",
    "market": "上市",
    "industry": "其他電子業",
    "concepts": [
      "其他電子業"
    ],
    "close": 336.0,
    "changePercent": 9.98,
    "volume": 869242,
    "tradeValue": 284720752.0,
    "listedShares": 104609000,
    "turnoverRate": 0.8309,
    "peRatio": 254.55,
    "pbRatio": 5.12,
    "dividendYield": 0.3,
    "revenueMonth": "2026-05",
    "revenueMillion": 155.71,
    "revenueMomPct": 9.54,
    "revenueYoyPct": 27.05,
    "fundamentalScore": 54.1,
    "technicalScore": 70,
    "chipScore": 80.7,
    "turnoverScore": 74.4,
    "totalScore": 68.6,
    "tradeType": "波段",
    "riskLabel": "過熱",
    "updatedAt": "2026-07-04T01:08:05+08:00",
    "dataDate": "2026-07-02",
    "scoreSource": "official_quote_valuation_revenue",
    "rank": 97
  },
  {
    "code": "6944",
    "symbol": "6944",
    "name": "兆聯實業",
    "market": "上市",
    "industry": "綠能環保",
    "concepts": [
      "綠能環保"
    ],
    "close": 1010.0,
    "changePercent": 4.55,
    "volume": 519070,
    "tradeValue": 513963364.0,
    "listedShares": 76687912,
    "turnoverRate": 0.6769,
    "peRatio": 28.42,
    "pbRatio": 8.74,
    "dividendYield": 1.98,
    "revenueMonth": "2026-05",
    "revenueMillion": 1671.46,
    "revenueMomPct": 10.15,
    "revenueYoyPct": 48.23,
    "fundamentalScore": 62.9,
    "technicalScore": 65.7,
    "chipScore": 77.6,
    "turnoverScore": 70.8,
    "totalScore": 68.6,
    "tradeType": "中長期",
    "riskLabel": "正常",
    "updatedAt": "2026-07-04T01:08:05+08:00",
    "dataDate": "2026-07-02",
    "scoreSource": "official_quote_valuation_revenue",
    "rank": 98
  },
  {
    "code": "1466",
    "symbol": "1466",
    "name": "聚隆",
    "market": "上市",
    "industry": "紡織纖維",
    "concepts": [
      "紡織纖維"
    ],
    "close": 17.85,
    "changePercent": 9.85,
    "volume": 4158740,
    "tradeValue": 68391909.0,
    "listedShares": 111157320,
    "turnoverRate": 3.7413,
    "peRatio": null,
    "pbRatio": 1.27,
    "dividendYield": 1.12,
    "revenueMonth": "2026-05",
    "revenueMillion": 192.09,
    "revenueMomPct": 2.5,
    "revenueYoyPct": 4.6,
    "fundamentalScore": 58.5,
    "technicalScore": 70,
    "chipScore": 65.2,
    "turnoverScore": 90.7,
    "totalScore": 68.5,
    "tradeType": "波段",
    "riskLabel": "過熱",
    "updatedAt": "2026-07-04T01:08:05+08:00",
    "dataDate": "2026-07-02",
    "scoreSource": "official_quote_valuation_revenue",
    "rank": 99
  },
  {
    "code": "2236",
    "symbol": "2236",
    "name": "百達-KY",
    "market": "上市",
    "industry": "汽車工業",
    "concepts": [
      "汽車工業"
    ],
    "close": 167.5,
    "changePercent": 4.04,
    "volume": 1708208,
    "tradeValue": 282683753.0,
    "listedShares": 62130976,
    "turnoverRate": 2.7494,
    "peRatio": null,
    "pbRatio": 4.45,
    "dividendYield": 0.39,
    "revenueMonth": "2026-05",
    "revenueMillion": 1067.37,
    "revenueMomPct": 11.8,
    "revenueYoyPct": 27.34,
    "fundamentalScore": 60.3,
    "technicalScore": 64.1,
    "chipScore": 72.1,
    "turnoverScore": 87.7,
    "totalScore": 68.5,
    "tradeType": "中長期",
    "riskLabel": "正常",
    "updatedAt": "2026-07-04T01:08:05+08:00",
    "dataDate": "2026-07-02",
    "scoreSource": "official_quote_valuation_revenue",
    "rank": 100
  }
]
